{
  "file_path": "C:\\Users\\lenovo\\Desktop\\project\\markdown_files\\黄山谷捷_招股说明书_2026.md",
  "relevant_sections": [
    {
      "title_hierarchy": [
        "首次公开发行股票并在创业板上市行股票并在",
        "、发行人现代企业制度的建立健全情况"
      ],
      "content": [
        "司根据《公司法》《证券法》《上市公司治理准则》《上市公司章程指引等法律法规的要求，建和完善了由股东大会、董事会、监事会、级管理员组成的公司治理架构，形成了权力机构、决策机构、监督机构和管理层之间各司其职、各负其责、协调运作、有效制衡的现代公司治理结构。",
        "公司按照《深圳证券交易所创业板股票上市规则》等件的要求，有效执了公司制定的各项内部控制制度，保障公司高效可靠运行，公司内部控制制度健全有效并得到有效执行。"
      ],
      "matched_keyword": "股东"
    },
    {
      "title_hierarchy": [
        "首次公开发行股票并在创业板上市行股票并在",
        "四、发行人持续经营能力及未来发展规划"
      ],
      "content": [
        "经过多年业务积淀，公司已在国内外形成较强的行业优势竞争地位。报告期内，公司营业收入分别为 25,544.79 万元、53,665.14 万元、75,898.64 万元和27,901.55 万元，2021-2023 年复合增长率 72.37%，扣除非经常性损益后归属于母公司所有者的净利润分别为 3,398.34 万元、9,671.78 万元、14,529.21 万元和 5,221.40 万元，2021-2023 年复合增长率 106.77%。公司行业地位较为突出，能够积极防范和应对各种不利风险因素，具有良好的持续经营能力。",
        "公司致力于成为全球领先的功率半导体模块散热基板研发和制造企业。公司将以车规级功率模块散热基板业务为核心，积极拓展自身散热基板产品在风力发电、光伏发电、轨道交通和其他电气化交通工具等领域的创新运用，持续为产业和股东创造价值。",
        "公司董事长：",
        "![](images/cb4e52beb0a19c20660a745f8ffcfb27b42fda972635636a33c9152d9a6e9b14.jpg)",
        "<details>",
        "<summary>seal</summary>",
        "黄山谷捷股份有公司",
        "3410040127944",
        "</details>",
        "本次发行概况",
        "![](images/fb7038b4bab22369fa94b3ea0da87879184a08579acdc27a20816a35f670bb95.jpg)"
      ],
      "matched_keyword": "股东"
    },
    {
      "title_hierarchy": [
        "首次公开发行股票并在创业板上市行股票并在",
        "目 录"
      ],
      "content": [
        "声 明......",
        "致投资者的声明 ......",
        "本次发行概况 ...",
        "目 录.....",
        "第一节 释义 .. .. 9",
        "一、一般名词释义. ... 9",
        "二、专用术语释义.. .. 10",
        "第二节 概览 ..... ... 13",
        "一、重大事项提示.. .... 13",
        "二、发行人及本次发行的中介机构基本情况.. ..... 16",
        "三、本次发行概况.. .... 17",
        "四、主营业务经营情况.. ... 18",
        "五、发行人板块定位... .. 21",
        "六、报告期的主要财务数据及财务指标.. .. 26",
        "七、公司财务报告审计截止日后的主要财务信息及经营状况. . 27",
        "八、发行人选择的具体上市标准.. . 29",
        "九、发行人的募集资金用途与未来发展规划.. .. 29",
        "十、其他对发行人有重大影响的事项... ... 30",
        "第三节 风险因素 .... .. 31",
        "一、与发行人相关风险.. ..31",
        "二、与行业相关的风险. . 34",
        "三、其他风险... . 35",
        "第四节 发行人基本情况 .. . 37",
        "一、发行人概况.. . 37",
        "二、发行人的设立情况、报告期内的股本和股东变化情况. .. 37",
        "三、发行人成立以来的重要事件... ... 45",
        "四、发行人在其他证券市场的上市/挂牌情况 . .. 47",
        "五、发行人的股权结构和组织结构... ..47",
        "六、发行人控股子公司、参股公司情况....... ...... 48",
        "七、持有发行人 5%以上股份或表决权的主要股东及实际控制人情况 .......49",
        "八、特别表决权股份或类似安排情况... .... 57",
        "九、协议控制架构情况... ... 57",
        "十、控股股东、实际控制人的合法合规情况... ......... 57",
        "十一、发行人股本情况.....",
        "十二、董事、监事、高级管理人员与其他核心人员. .... 64",
        "十三、发行人本次公开发行申报前已经制定或实施的股权激励及相关安排",
        "...... 77",
        "十四、发行人员工情况.. ... 78",
        "第五节 业务与技术 .... ... 82",
        "一、发行人主营业务和主要产品情况. ... 82",
        "二、发行人所处行业基本情况及其竞争状况.. ...... 93",
        "三、发行人报告期内销售情况和主要客户情况....... ..... 131",
        "四、发行人报告期内采购情况和主要供应商情况. ... 136",
        "五、公司经营相关的主要固定资产和无形资产等资源要素.. ..... 141",
        "六、发行人的核心技术及研发情况... ... 146",
        "七、发行人生产经营中涉及的主要环境污染物、主要处理设施及处理能力",
        ".. 158",
        "八、发行人境外生产经营情况. .. 159",
        "第六节 财务会计信息与管理层分析 ................................................................... 160",
        "一、财务报表.... ...... 160",
        "二、审计意见、关键审计事项. ... 165",
        "三、重大事项或重要性水平判断标准......... ...... 165",
        "四、影响经营业绩的重要因素.. .. 166",
        "五、财务报表的编制基础及合并财务报表范围. ... 168",
        "六、主要会计政策和会计估计... ... 169",
        "七、非经常性损益... .. 196",
        "八、主要税项...... ... 197",
        "九、主要财务指标.. ..198",
        "十、经营成果分析.... .. 200",
        "十一、资产质量分析.. .. 222",
        "十二、偿债能力、流动性与持续经营能力分析. ... 240",
        "十三、重大投资、资本性支出、重大资产业务重组或股权收购合并事项252",
        "十四、资产负债表日后事项、或有事项、其他重要事项以及重大担保、诉讼",
        "等事项...... ..... 253",
        "十五、盈利预测报告... .. 253",
        "十六、财务报告截止日后发行人主要财务信息及经营状况.. ..... 253",
        "第七节 募集资金运用与未来发展规划... ... 256",
        "一、募集资金运用概况...... ..................... .. 256",
        "二、募集资金投资项目具体情况.... .. 260",
        "三、公司战略规划及采取的措施.. .. 260",
        "第八节 公司治理与独立性 .... ... 264",
        "一、报告期内公司治理存在的缺陷及改进情况. ... 264",
        "二、报告期内公司内部控制情况..... .... 264",
        "三、发行人报告期内的违法违规及受到处罚、监督管理措施、纪律处分或自",
        "律监管措施的情况.. ... 266",
        "四、发行人报告期内的资金占用和对外担保情况. ..... 266",
        "五、发行人直接面向市场独立持续经营的能力... ... 266",
        "六、同业竞争情况.... .. 268",
        "七、关联方、关联关系和关联交易... ... 268",
        "第九节 投资者保护 ... .. 281",
        "一、本次发行前滚存利润的分配安排... .... 281",
        "二、股利分配政策... .. 281",
        "..... 288",
        "一、重大商务合同................... ..... 288",
        "二、对外担保情况... .. 292",
        "三、重大诉讼或仲裁事项.. ... 292",
        "第十一节 声明 ..... ... 294",
        "一、发行人及全体董事、监事、高级管理人员声明.... ..294",
        "二、发行人控股股东声明. .295",
        "三、发行人实际控制人声明.. .296",
        "四、保荐机构（主承销商）声明. .297",
        "五、发行人律师声明.. .299",
        "六、会计师事务所声明. .300",
        "七、资产评估机构声明. .301",
        "八、资产评估复核机构声明.. .302",
        "九、验资机构声明.. .. 303",
        "第十二节 附件 ... .. 304",
        "一、附件目录.. .304",
        "二、查阅时间及地点. .. 305",
        "三、落实投资者关系管理相关规定的安排、股利分配决策程序、股东投票机",
        "制建立情况.. .. 305",
        "四、本次发行相关主体作出的重要承诺. .. 308",
        "五、股东大会、董事会、监事会、独立董事、董事会秘书以及审计委员会等",
        "机构的运行及履职情况. .. 330",
        "六、募集资金具体运用情况.. .333",
        "七、子公司、参股公司简要情况. .342"
      ],
      "matched_keyword": "股权结构"
    },
    {
      "title_hierarchy": [
        "首次公开发行股票并在创业板上市行股票并在",
        "2、经营业绩下滑的风险"
      ],
      "content": [
        "受海外新能源汽车政策调整、产品单价下滑和铜价持续上涨等因素影响，2024 年上半年以来公司营业收入及扣除非经常性损益后归属于母公司股东净利润较上年同期有所下降。如果未来新能源汽车行业政策出现较大不利变化、新能源汽车市场价格竞争加剧、铜价持续上涨等因素进一步导致产品销售单价和毛利率下滑，给公司盈利能力造成较大不利影响，公司将面临经营业绩下滑的风险。"
      ],
      "matched_keyword": "股东"
    },
    {
      "title_hierarchy": [
        "首次公开发行股票并在创业板上市行股票并在",
        "（二）关于滚存利润的分配及上市后的现金股利分配方案"
      ],
      "content": [
        "公司 2023 年第一次临时股东大会审议通过了《关于公司首次公开发行股票并在创业板上市前滚存利润分配方案的议案》，同意公司本次发行前的滚存未分配利润由本次发行后的新老股东按照发行后的持股比例共享。",
        "本公司提示投资者认真阅读公司发行上市后的利润分配政策、现金分红的最低比例、上市后三年内利润分配计划和长期回报规划，具体事项详见本招股说明书“第九节 投资者保护”之“二、股利分配政策”相关内容。"
      ],
      "matched_keyword": "股东"
    },
    {
      "title_hierarchy": [
        "首次公开发行股票并在创业板上市行股票并在",
        "（三）本次发行相关主体作出的重要承诺"
      ],
      "content": [
        "公司控股股东、实际控制人及其一致行动人已承诺，若出现公司上市当年或之后第二年、第三年较上市前一年扣除非经常性损益后归母净利润下滑 50%以上等情形的，延长其届时所持股份锁定期限。本公司提示投资者认真阅读本公司、股东、实际控制人、董事、监事、高级管理人员、其他核心人员以及本次发行的保荐人及证券服务机构等作出的重要承诺以及未能履行承诺的约束措施，具体承诺事项详见本招股说明书“第十二节 附件”之“四、本次发行相关主体作出的重要承诺”。"
      ],
      "matched_keyword": "股东"
    },
    {
      "title_hierarchy": [
        "首次公开发行股票并在创业板上市行股票并在",
        "2、合并利润表主要数据"
      ],
      "content": [
        "单位：万元",
        "![](images/ab5675027fc3c375e62775cde3b5d45c399622e285525d74ed15dd0e855d62ef.jpg)",
        "2024 年 1-9 月公司营业收入为 48,201.72 万元，较上年同期下降 13.80%；扣除非经常性损益后归属于母公司股东的净利润为 8,113.14 万元，较上年同期下降22.73%，主要受国外新能源汽车政策放缓、新能源汽车价格战向上游传导以及铜价上涨的影响。"
      ],
      "matched_keyword": "股东"
    },
    {
      "title_hierarchy": [
        "首次公开发行股票并在创业板上市行股票并在",
        "八、发行人选择的具体上市标准"
      ],
      "content": [
        "根据《深圳证券交易所创业板股票上市规则（2024 年修订）》规定的上市条件，发行人符合上市标准为“2.1.2（一）最近两年净利润均为正，累计净利润不低于1亿元，且最近一年净利润不低于 6,000 万元”，具体如下：",
        "根据中审众环会计师出具的《审计报告》（众环审字（2024）0104198 号），发行人2022年度、2023年度的扣除非经常性损益前后孰低的归属于母公司股东的净利润分别为 9,671.78 万元和 14,529.21 万元，合计 24,201.00 万元，不低于 1亿元，2023 年度扣除非经常性损益前后孰低的归属于母公司股东的净利润不低于 6,000 万元。"
      ],
      "matched_keyword": "股东"
    },
    {
      "title_hierarchy": [
        "首次公开发行股票并在创业板上市行股票并在",
        "九、发行人的募集资金用途与未来发展规划"
      ],
      "content": [
        "经发行人 2023 年第一次临时股东大会审议确定的本次募集资金投资项目及",
        "其备案情况如下：",
        "单位：万元",
        "![](images/db800e4b195f9af0704c06b8ccb4865e35bacdd5562fa0b57c816b5471e28281.jpg)",
        "若本次股票发行后，实际募集资金数额（扣除发行费用后）大于上述投资项目的资金需求，超过部分将根据中国证监会及深圳证券交易所的有关规定用于公司主营业务的发展。若本次股票发行后，实际募集资金数量（扣除发行费用后）小于上述投资项目的资金需求，不足部分公司将用自筹资金补足。如果本次募集资金到位前，公司需要对上述拟投资项目进行先期投入，则公司将用自筹资金投入，待募集资金到位后以募集资金置换自筹资金。",
        "本次募集资金运用与未来发展规划具体情况详见本招股说明书“第七节募集资金运用与未来发展规划”。"
      ],
      "matched_keyword": "股东"
    },
    {
      "title_hierarchy": [
        "首次公开发行股票并在创业板上市行股票并在",
        "（二）经营业绩下滑的风险"
      ],
      "content": [
        "受海外新能源汽车政策调整、产品单价下滑和铜价持续上涨等因素影响，2024 年上半年以来公司营业收入及扣除非经常性损益后归属于母公司股东净利润较上年同期有所下降。如果未来新能源汽车行业政策出现较大不利变化、新能源汽车市场价格竞争加剧、铜价持续上涨等因素进一步导致产品销售单价和毛利率下滑，给公司盈利能力造成较大不利影响，公司将面临经营业绩下滑的风险。"
      ],
      "matched_keyword": "股东"
    },
    {
      "title_hierarchy": [
        "首次公开发行股票并在创业板上市行股票并在",
        "1、有限公司设立情况"
      ],
      "content": [
        "2012年4月11日，黄山市供销社出具《关于同意投资昆山谷捷项目的批复》（黄供财[2012]22 号），同意设立谷捷有限。",
        "2012年5月28 日，谷捷有限股东昆山谷捷作出股东决定，同意由昆山谷捷出资1,000万元，设立谷捷有限。",
        "2012年6月12 日，安徽天正达会计师事务所出具《验资报告》（皖天会验字[2012]第261号），确认截至 2012年6月 12日，谷捷有限已收到昆山谷捷缴纳的注册资本1,000 万元，出资方式为货币。",
        "2012 年 6 月 12 日，谷捷有限取得了黄山市工商行政管理局徽州区分局核发的营业执照（注册号：341004000012276）。",
        "设立时，谷捷有限的股权结构如下：",
        "![](images/98eaced6a0f264b2d81f43b79fa4ec454f7afbaf2a8321b067b17fafd095347d.jpg)"
      ],
      "matched_keyword": "股权结构"
    },
    {
      "title_hierarchy": [
        "首次公开发行股票并在创业板上市行股票并在",
        "2、股份公司设立情况"
      ],
      "content": [
        "2022 年 8 月 5 日，中审众环会计师出具《审计报告》（众环审字（2022）0113941号），确认截至2022年5月31日，谷捷有限经审计后的净资产为20,152.51万元。",
        "2022年8月7日，中联国信出具《资产评估报告》（皖中联国信评报字（2022）第 223 号），确认截至 2022 年 5 月 31 日，谷捷有限净资产评估值为 28,244.00万元。",
        "2022 年 8 月 24 日，黄山市供销社、黄山供销集团出具《关于黄山谷捷散热科技有限公司整体改制变更设立股份有限公司的批复》（黄供集团[2022]44 号）注1，同意谷捷有限整体变更为股份有限公司。",
        "2022年8月24 日，谷捷有限召开股东会，同意将谷捷有限变更为股份有限公司，以截至 2022 年 5 月 31 日经审计的净资产 20,152.51 万元按 1:0.29773 比例折成 6,000 万股作为发行人总股本，每股面值 1 元，净资产余额 14,152.51 万元转为股份有限公司的资本公积，整体变更后各股东持股比例保持不变。",
        "2022 年 8 月 24 日，谷捷有限全体股东签订《黄山谷捷股份有限公司发起人协议》。",
        "2022 年 9 月 8 日，公司召开创立大会暨首次股东大会，审议通过了公司章程并选举产生了第一届董事会和监事会。",
        "2022 年 9 月 8 日，中审众环会计师出具《验资报告》（众环验字（2022）",
        "0110090 号），确认截至 2022 年 9 月 8 日，黄山谷捷已收到全体股东缴纳的实",
        "收资本 6,000.00 万元，出资方式为净资产折股。",
        "2022年9月13 日，黄山谷捷取得了黄山市市场监督管理局为其换发的营业执照（统一社会信用代码：913410045986552970）。",
        "本次整体变更后，黄山谷捷的股权结构如下：",
        "![](images/4cd61aeb18feeaf488ed8e4dda8da645ca4716d085a5e2f37bf3107da149015b.jpg)"
      ],
      "matched_keyword": "股权结构"
    },
    {
      "title_hierarchy": [
        "首次公开发行股票并在创业板上市行股票并在",
        "（二）发行人报告期内的股本和股东变化情况"
      ],
      "content": [
        "![](images/b581e802e92ca00744588a68004eef565dfe2dac3436683e47e4665b896ccd5d.jpg)"
      ],
      "matched_keyword": "股东"
    },
    {
      "title_hierarchy": [
        "首次公开发行股票并在创业板上市行股票并在",
        "1、报告期期初股本和股东情况"
      ],
      "content": [
        "自有限公司设立至报告期期初，公司的股本及股东情况未发生变化，具体情况见本节之“二、发行人的设立情况、报告期内的股本和股东变化情况”之“（一）发行人的设立情况”之“1、有限公司设立情况”。"
      ],
      "matched_keyword": "股东"
    },
    {
      "title_hierarchy": [
        "首次公开发行股票并在创业板上市行股票并在",
        "2、2021年 4月，第一次股权转让"
      ],
      "content": [
        "2020 年 12 月 30 日，黄山市供销社、黄山供销集团出具《关于同意昆山谷捷股权转让以及黄山谷捷吸收合并昆山谷捷的批复》（黄供集团[2020]80 号），同意昆山谷捷将其所持谷捷有限 78%、11%、11%的股权以零对价分别转让给黄山供销集团、张俊武、周斌。",
        "2021 年 4 月 3 日，谷捷有限股东昆山谷捷作出股东决定，同意昆山谷捷进行股权转让，受让方系昆山谷捷全体股东，各股东按持有昆山谷捷的股权比例受让谷捷有限股权。同日，昆山谷捷分别与黄山供销集团、张俊武、周斌签署了股权转让相关协议。",
        "转让前后，谷捷有限的股权结构图对比如下：",
        "![](images/39651c204514737668d173914b1b4b91e9bbbb362bff4ae689de3dba8b33d304.jpg)",
        "2021 年 4 月 7 日，谷捷有限取得了黄山市徽州区市场监督管理局为其换发的营业执照（统一社会信用代码：913410045986552970）。",
        "本次股权转让后，谷捷有限的股权结构如下：",
        "![](images/30f19fab8e857206f062ea564ddd59ff71aa8ccf066eba004ef679860925dcc0.jpg)",
        "本次股权转让系同一股权结构下的公司架构调整，股权转让完成后，黄山供销集团、张俊武、周斌对谷捷有限的持股方式由间接持股变更为直接持股，本次股权转让价格为 0 元。"
      ],
      "matched_keyword": "股权转让"
    },
    {
      "title_hierarchy": [
        "首次公开发行股票并在创业板上市行股票并在",
        "3、2021 年 4 月，吸收合并"
      ],
      "content": [
        "2020 年 12 月 24 日，谷捷有限及昆山谷捷召开股东会，同意谷捷有限吸收合并昆山谷捷，合并后谷捷有限存续，昆山谷捷注销；同日，谷捷有限与昆山谷捷签订《合并协议》。",
        "2020 年 12 月 25 日，谷捷有限与昆山谷捷在《中国商报》联合刊登了吸收合并公告，按照《公司法》规定履行了债权人告知等义务。公告期满，未有债权人要求谷捷有限清偿债务或要求谷捷有限提供相应担保。",
        "2020 年 12 月 30 日，黄山市供销社、黄山供销集团出具《关于同意昆山谷捷股权转让以及黄山谷捷吸收合并昆山谷捷的批复》（黄供集团[2020]80 号），同意谷捷有限吸收合并昆山谷捷，吸收合并后昆山谷捷注销，谷捷有限存续。",
        "2021 年 4 月 7 日，谷捷有限召开股东会，吸收合并后谷捷有限的注册资本变更为1,200万元，其中黄山供销集团出资 936万元，张俊武出资 132万元，周斌出资132万元；同日，谷捷有限与昆山谷捷再次签订《吸收合并协议》，进一步明确了双方权利义务等条款。",
        "2021 年 4 月 13 日，谷捷有限取得了黄山市徽州区市场监督管理局为其换发的营业执照（统一社会信用代码：913410045986552970）。",
        "2021年8月20 日，国家税务总局苏州昆山经济技术开发区税务局出具《清税证明》（昆开税税企清[2021]9296 号），确认昆山谷捷税务事项已结清。2021年 9 月 7 日，昆山市市场监督管理局出具《准予注销登记通知书》（（05831101zc）公司注销[2021]第 09070003 号），核准昆山谷捷注销。",
        "2022年11月16 日，中审众环会计师出具《验资报告》（众环验字（2022）0110095 号），确认截至 2021 年 9 月 7 日，谷捷有限已收到全体股东新增实收资本200万元，由股东以被合并方昆山谷捷的账面净资产出资。",
        "本次吸收合并前后，谷捷有限、昆山谷捷的股东及各出资比例如下：",
        "单位：万元",
        "![](images/2f2788a27703c33c2aec87884ddda55929ccbe1c01eaa07e820ad998a1df6a5c.jpg)",
        "本次吸收合并系同一股权结构下的公司架构调整，吸收合并当时未对双方净资产进行评估。2022 年 11 月 14 日，中联国信进行了追溯评估并出具了《资产评估报告》（皖中联国信评报字（2022）第 303-1号、皖中联国信评报字（2022）第303-2号），确认截至 2021年3月31日，昆山谷捷净资产账面价值为 380.94万元，评估价值为 380.94 万元，谷捷有限净资产账面价值为 2,912.30 万元，评估价值为 9,651.75 万元。"
      ],
      "matched_keyword": "股权结构"
    },
    {
      "title_hierarchy": [
        "首次公开发行股票并在创业板上市行股票并在",
        "4、2021 年 11 月，第一次增资，增资至 1,714.2857 万元"
      ],
      "content": [
        "2021年7月31 日，黄山江南新科苑资产评估事务所（特殊普通合伙）出具《资产评估报告》（新科苑评报字（2021）第 0112 号），确认截至 2020 年 12月 31 日，谷捷有限股东全部权益价值为 26,461.86 万元。2022 年 11 月 25 日，中联国信出具《评估复核报告》（皖中联国信复核字（2022）第 002 号），认为评估结果基本反映了资产在评估基准日的市场价值。",
        "2021年9月17 日，黄山市供销社、黄山供销集团出具《关于黄山谷捷散热科技有限公司增资扩股有关事项的批复》（黄供集团[2021]52 号），同意谷捷有限增资扩股，由赛格高技术和上汽科技向谷捷有限增资。",
        "2021年9月18 日，赛格高技术、上汽科技与黄山供销集团、张俊武、周斌及谷捷有限签署《黄山谷捷散热科技有限公司增资协议》，约定谷捷有限增加注册资本514.2857万元，其中赛格高技术认缴462.8571万元、上汽科技认缴51.4286万元，增资价格为 22.42元/注册资本，出资方式为货币。各方在增资协议中约定了回购条款及其他股东特殊权利条款，相关内容及解除情况详见本节之“十一、发行人股本情况”之“（十）本次发行前涉及的对赌协议及其解除情况”。",
        "2021 年 9 月 19 日，谷捷有限召开股东会，同意上述增资扩股事项。",
        "2021 年 11 月 11 日，谷捷有限取得了黄山市市场监督管理局为其换发的营业执照（统一社会信用代码：913410045986552970）。",
        "2022 年 1 月 17 日，中审众环会计师出具《验资报告》（众环验字（2022）0110017 号），确认截至 2021 年 12 月 31 日，谷捷有限已收到股东赛格高技术和上汽科技缴纳的实收资本514.2857万元，出资方式为货币。",
        "本次增资完成后，公司股权结构如下：",
        "![](images/e198a8d972782ee598fe59ac1ee9e51be3144053021c1dea1af250c00da0adcf.jpg)"
      ],
      "matched_keyword": "增资"
    },
    {
      "title_hierarchy": [
        "首次公开发行股票并在创业板上市行股票并在",
        "5、2022 年 5 月，第二次增资，增资至 1,804.5113 万元"
      ],
      "content": [
        "2022年4月28日，中联国信出具《资产评估报告》（皖中联国信评报字（2022）第 171 号），确认截至 2021 年 12 月 31 日，谷捷有限股东全部权益的市场价值为 40,370 万元。",
        "2022年5月17 日，黄山市供销社、黄山供销集团出具《关于黄山谷捷散热科技有限公司员工股权激励实施方案的批复》（黄供集团[2022]27 号），同意谷捷有限实施员工股权激励。",
        "2022 年 5 月 20 日，谷捷有限召开股东会，同意将公司的注册资本由1,714.2857 万元增至 1,804.5113 万元，新增注册资本 90.2256 万元由员工持股平台黄山佳捷全额认缴。",
        "2022年5月24 日，谷捷有限与黄山佳捷签署《黄山谷捷散热科技有限公司增资扩股协议》，新增注册资本 90.2256 万元由黄山佳捷全额认缴，增资价格为23.55元/注册资本，出资方式为货币。",
        "2022年5月26 日，谷捷有限取得了黄山市市场监督管理局为其换发的营业",
        "执照（统一社会信用代码：913410045986552970）。",
        "2022 年 7 月 15 日，中审众环会计师出具《验资报告》（众环验字（2022）0110088号），确认截至 2022年5月31日，谷捷有限已收到股东黄山佳捷缴纳的实收资本90.2256 万元，出资方式为货币。",
        "本次增资完成后，谷捷有限的股权结构如下：",
        "![](images/ebb7563d208ba7e2c2cb8b61a537f143e5668b0a3993db84a17a8912fabdb609.jpg)"
      ],
      "matched_keyword": "增资"
    },
    {
      "title_hierarchy": [
        "首次公开发行股票并在创业板上市行股票并在",
        "6、2022 年 9 月，整体变更为股份公司"
      ],
      "content": [
        "2022 年 9 月，谷捷有限整体变更为股份公司，具体情况见本节之“二、发行人的设立情况、报告期内的股本和股东变化情况”之“（一）发行人的设立情况”之“2、股份公司设立情况”。"
      ],
      "matched_keyword": "股东"
    },
    {
      "title_hierarchy": [
        "首次公开发行股票并在创业板上市行股票并在",
        "2、吸收合并前，昆山谷捷历次股权和股东变化情况"
      ],
      "content": [
        "2009年6月30 日，昆山谷捷召开股东会，审议通过《昆山谷捷金属制品有限公司章程》。根据该公司章程，昆山谷捷设立时注册资本为 100 万元，其中吴斌认缴出资 60 万元；张俊武认缴出资 20 万元；邓亮认缴出资 10 万元；王凌峰认缴出资10万元。",
        "2010年3月22日，昆山谷捷召开股东会，同意王凌峰将其所持昆山谷捷10%股权转让给周斌，邓亮将其所持昆山谷捷 10%股权转让给周斌；同日，周斌分别与王凌峰、邓亮签订《股权转让协议》。",
        "2012年4月23 日，昆山谷捷召开股东会，同意新增注册资本 100万元，黄山市化工总厂、吴斌、张俊武、周斌分别认购 90万元、6万元、2万元、2万元。",
        "2014 年 6 月 7 日，吴斌与黄山市化工总厂签订《股权转让协议》，约定吴斌将其持有昆山谷捷 33%的股权转让给黄山市化工总厂；同日，昆山谷捷召开股东会，通过了股权转让后的章程修正案。",
        "2016年9月28 日，昆山谷捷召开股东会，决议股东黄山市化工总厂的名称变更为黄山供销集团。",
        "至本次吸收合并前，昆山谷捷的股权未再有其他变化。"
      ],
      "matched_keyword": "股东"
    },
    {
      "title_hierarchy": [
        "首次公开发行股票并在创业板上市行股票并在",
        "3、吸收合并的具体内容及履行的法定程序"
      ],
      "content": [
        "本次吸收合并的具体内容及履行的法定程序详见本节之“二、发行人的设立情况、报告期内的股本和股东变化情况”之“（二）发行人报告期内的股本和股东变化情况”之“3、2021 年 4 月，吸收合并”。"
      ],
      "matched_keyword": "股东"
    },
    {
      "title_hierarchy": [
        "首次公开发行股票并在创业板上市行股票并在",
        "4、上述吸收合并对发行人的影响"
      ],
      "content": [
        "本次吸收合并于 2021 年 4 月完成，吸收合并前一年被吸收合并方昆山谷捷与吸收合并方谷捷有限的资产总额、营业收入、利润总额情况如下：",
        "![](images/52817906d441eff9087af6834c78785dd6e8a896993689aee4b6085b4aa547c7.jpg)",
        "本次交易标的 2020年末/年度资产总额、营业收入、利润总额占吸收合并前谷捷有限相应项目的比例分别为 21.82%、0.00%、0.00%。被吸收合并方昆山谷捷系谷捷有限原控股股东，自报告期初起即与发行人受同一实际控制人控制。本次吸收合并完成后，公司的管理层和实际控制人没有发生变更，主营业务亦没有发生变化。本次吸收合并有利于精简组织架构、降低管理成本。"
      ],
      "matched_keyword": "股东"
    },
    {
      "title_hierarchy": [
        "首次公开发行股票并在创业板上市行股票并在",
        "四、发行人在其他证券市场的上市/挂牌情况"
      ],
      "content": [
        "谷捷有限于 2018 年 10 月 29 日在安徽股权托管交易中心挂牌，2022 年 11月24日终止在安徽股权托管交易中心挂牌。2022年12月30日，安徽股权托管交易中心出具证明，确认公司仅通过该中心进行股权登记托管，未通过该中心进行过股票发行、股权转让、股权质押、增减资等行为，公司未有受到该中心处罚的情形。"
      ],
      "matched_keyword": "股权转让"
    },
    {
      "title_hierarchy": [
        "首次公开发行股票并在创业板上市行股票并在",
        "（一）股权结构图"
      ],
      "content": [
        "截至本招股说明书签署日，公司股权结构如下图所示：",
        "![](images/c2a1d1e3fa05a3e91ca987dd7cf66bb2023d8289a724806ff3a5f161dd7d4705.jpg)"
      ],
      "matched_keyword": "股权结构"
    },
    {
      "title_hierarchy": [
        "首次公开发行股票并在创业板上市行股票并在",
        "（一）黄山广捷表面处理科技有限公司"
      ],
      "content": [
        "![](images/12bcc212f1e637fd0016073ff90c6c369956a416310bffd4998e32a7871a34c7.jpg)",
        "注 1：成立时黄山广捷系发行人持股 45%的联营企业，2022 年 5 月成为黄山谷捷的控股子公司；",
        "注2：以上财务数据已经中审众环会计师审计。",
        "七、持有发行人 5%以上股份或表决权的主要股东及实际控制人情况"
      ],
      "matched_keyword": "股东"
    },
    {
      "title_hierarchy": [
        "首次公开发行股票并在创业板上市行股票并在",
        "1、控股股东"
      ],
      "content": [
        "截至本招股说明书签署日，黄山供销集团持有发行人3,112.20 万股，持股比例为51.87%，为发行人的控股股东。黄山供销集团基本情况如下：",
        "![](images/5c5bca90dadcbd0257097b8ad68cddcff6ab72593cebb4e919897015229f334e.jpg)",
        "![](images/3aa0c0aae704c05c57c0dd695cb05bf23d2fe915ed8130f443ecc1ff9f40a479.jpg)",
        "注：2023 年度财务数据已经黄山徽泓会计师事务所（普通合伙）审计，2024 年 1-6 月财务数据未经审计。"
      ],
      "matched_keyword": "股东"
    },
    {
      "title_hierarchy": [
        "首次公开发行股票并在创业板上市行股票并在",
        "（二）控股股东和实际控制人直接或间接持有发行人的股份被质押、冻结或发生诉讼纠纷等情形"
      ],
      "content": [
        "截至本招股说明书签署日，发行人控股股东、实际控制人直接或间接持有发行人的股份均不存在质押、冻结或诉讼纠纷等情形。"
      ],
      "matched_keyword": "股东"
    },
    {
      "title_hierarchy": [
        "首次公开发行股票并在创业板上市行股票并在",
        "（三）其他持有发行人 5%以上股份或表决权的主要股东的基本情况"
      ],
      "content": [
        "截至本招股说明书签署日，除发行人控股股东黄山供销集团外，其他持有公司5%以上股份的股东为赛格高技术、张俊武、周斌和黄山佳捷，具体情况如下："
      ],
      "matched_keyword": "股东"
    },
    {
      "title_hierarchy": [
        "首次公开发行股票并在创业板上市行股票并在",
        "1、自然人股东"
      ],
      "content": [
        "截至本招股说明书签署日，张俊武直接持有发行人 438.90 万股，占发行人本次发行前总股本的 7.315%，周斌直接持有发行人 438.90 万股，占发行人本次发行前总股本的7.315%。自然人股东的身份证号及住所信息如下：",
        "![](images/4d2dca6dd2cefe94cd35c5af484db3f7af12bc7c1673484849bba2b640b1aed2.jpg)",
        "张俊武及周斌简历详见本节”之“十二、董事、监事、高级管理人员与其他核心人员”之“（一）董事、监事、高级管理人员及其他核心人员的简介”之“1、董事会成员”。"
      ],
      "matched_keyword": "股东"
    },
    {
      "title_hierarchy": [
        "首次公开发行股票并在创业板上市行股票并在",
        "3、黄山佳捷股权管理中心（有限合伙）"
      ],
      "content": [
        "黄山佳捷持有发行人 300.00万股，占发行人本次公开发行前总股本的 5.00%，其基本情况如下：",
        "![](images/1a0f66f9a75f6b80fbe207d76786e8c00d7ba68748b6d6adc8a389e9c7e4c709.jpg)",
        "黄山佳捷为黄山谷捷的员工持股平台，截至本招股说明书签署日，合伙人出资情况如下：",
        "单位：万元",
        "![](images/992070a18045f035df7ae12c5d70cc543a076b6ba92b550706a729475e9e3a2f.jpg)",
        "![](images/0baba6aba69939e6d9a7dbe029fb0e93c954f666985824546826988cc584556a.jpg)",
        "（四）控股股东、实际控制人控制的其他企业",
        "截至本招股说明书签署日，除控制发行人外，控股股东、实际控制人控制的其他企业基本情况如下：",
        "![](images/48fcf5620f12b29d22912cf80cb12311b68e8a4d12454f6228722de817ac9ba0.jpg)",
        "![](images/745c8ce2bac0de93053322b3bd6ae18ad1f49e8e31ac822a30cb59093642cb87.jpg)",
        "![](images/fe2cc0c59edd9d255d82c34938df83d61e9fadd56e6e87fe543c2f0f98b19cc5.jpg)",
        "![](images/b507ea383cb0f0a928267b94dc4f2c05ffd266f7ba9cee3e0e0959e60ec8c05b.jpg)",
        "![](images/5f31dd8cd4f95248ff35cbcffe332979204947da82dddeb11abb32f730f727b3.jpg)"
      ],
      "matched_keyword": "股东"
    },
    {
      "title_hierarchy": [
        "首次公开发行股票并在创业板上市行股票并在",
        "十、控股股东、实际控制人的合法合规情况"
      ],
      "content": [
        "报告期内，控股股东、实际控制人不存在贪污、贿赂、侵占财产、挪用财产或者破坏社会主义市场经济秩序的刑事犯罪，不存在欺诈发行、重大信息披露违法或者其他涉及国家安全、公共安全、生态安全、生产安全、公众健康安全等领域的重大违法行为。"
      ],
      "matched_keyword": "股东"
    },
    {
      "title_hierarchy": [
        "首次公开发行股票并在创业板上市行股票并在",
        "（一）本次发行前后的股本情况"
      ],
      "content": [
        "本次发行前发行人总股本为 6,000 万股，本次拟公开发行不超过 2,000 万股股份，占本次发行后总股本的比例不低于 25.00%。按本次公开发行 2,000 万股计算，发行前后发行人的股本结构如下：",
        "![](images/27256bd66a3afb02f83688889d37aa56b909915628161e4d77704c87e72dd162.jpg)",
        "![](images/6b1ebf882b6ac75aec103496f89bee2911c68850d32c10bd412ef7c61ebead96.jpg)",
        "注：CS 指 Controlling State-owned Shareholder，国有实际控制股东，根据《深圳市国资委关于黄山谷捷股份有限公司国有股权管理有关问题的批复》（深国资委函[2023]182 号）认定，下同。"
      ],
      "matched_keyword": "股东"
    },
    {
      "title_hierarchy": [
        "首次公开发行股票并在创业板上市行股票并在",
        "（二）本次发行前的前十名股东情况"
      ],
      "content": [
        "本次发行前，发行人前十名股东的持股情况如下：",
        "![](images/02c2ec13fc0162625089e21b4e0f3c0cefee7c5692d8c0bc5960cc5afff3dff1.jpg)"
      ],
      "matched_keyword": "股东"
    },
    {
      "title_hierarchy": [
        "首次公开发行股票并在创业板上市行股票并在",
        "（三）本次发行前的前十名自然人股东及其在公司任职情况"
      ],
      "content": [
        "本次发行前，发行人的前十名自然人股东及其在发行人处任职的情况如下：",
        "![](images/5a2de785e582182af62784262ff1101fb504bb2908ec2e671f8bf9b15d8fc270.jpg)"
      ],
      "matched_keyword": "股东"
    },
    {
      "title_hierarchy": [
        "首次公开发行股票并在创业板上市行股票并在",
        "1、国有股份情况"
      ],
      "content": [
        "发行人股东中，赛格高技术为国有股东，持有发行人1,539万股，占发行人发行前总股本的 25.65%；上汽科技为国有股东且为境外主体，持有发行人 171万股，占发行人发行前总股本的 2.85%。",
        "2023年3月30 日，深圳市人民政府国有资产监督管理委员会出具《深圳市",
        "国资委关于黄山谷捷股份有限公司国有股权管理有关问题的批复》（深国资委函[2023]182 号），确认赛格高技术、上汽科技为国有实际控制股东，其在中国证券登记结算有限责任公司登记的投资者一码通账户应标注“CS”标识。"
      ],
      "matched_keyword": "股东"
    },
    {
      "title_hierarchy": [
        "首次公开发行股票并在创业板上市行股票并在",
        "2、外资股份情况"
      ],
      "content": [
        "公司股东中，上汽科技为外资股东，持有发行人 171万股，占发行人发行前总股本的2.85%，注册地为美国。"
      ],
      "matched_keyword": "股东"
    },
    {
      "title_hierarchy": [
        "首次公开发行股票并在创业板上市行股票并在",
        "1、新增股东的持股数量及变化情况、取得股份的时间、价格和定价依据"
      ],
      "content": [
        "发行人最近一年新增股东为黄山佳捷，系通过增资方式成为发行人股东。",
        "为建立、健全公司长效激励机制，吸引和留住优秀人才，2022 年 5 月 20 日谷捷有限召开股东会，决议由公司的 15 名激励对象通过新设员工持股平台黄山佳捷对公司增资，以 23.55 元/注册资本的价格认缴公司新增注册资本 90.2256 万元。2022 年 5 月 24 日，谷捷有限与黄山佳捷签署《黄山谷捷散热科技有限公司增资扩股协议》，黄山佳捷以 2,124.8129 万元认购发行人 90.2256 万元注册资本。",
        "本次增资价格及定价依据以资产评估结果为基准确定，亦不低于最近一次外部投资者的增资价格。"
      ],
      "matched_keyword": "股东"
    },
    {
      "title_hierarchy": [
        "首次公开发行股票并在创业板上市行股票并在",
        "2、新增股东基本情况"
      ],
      "content": [
        "黄山佳捷的基本情况详见本节之“七、持有发行人 5%以上股份或表决权的主要股东及实际控制人情况”之“（三）其他持有发行人 5%以上股份或表决权的主要股东的基本情况”之“3、黄山佳捷股权管理中心（有限合伙）”。",
        "3、新增股东与发行人其他股东、董事、监事、高级管理人员是否存在关联关系，新增股东与本次发行的中介机构及其负责人、高级管理人员、经办人员是否存在关联关系，新增股东是否存在股份代持情形",
        "黄山佳捷为员工持股平台，发行人董事、总经理、股东张俊武持有黄山佳捷14%的合伙份额并担任黄山佳捷执行事务合伙人，董事、副总经理、股东周斌持有黄山佳捷 7%的合伙份额，职工代表监事谷伟持有黄山佳捷 8%的合伙份额，副总经理罗仁棠持有黄山佳捷 13%的合伙份额，副总经理兼董事会秘书程家斌持有黄山佳捷10%的合伙份额，财务负责人汪琦持有黄山佳捷 7%的合伙份额。除上述情形外，发行人新增股东黄山佳捷与发行人其他股东、董事、监事、高级管理人员、本次发行中介机构及其负责人、高级管理人员、经办人员之间不存在关联关系，新增股东不存在股份代持情形。"
      ],
      "matched_keyword": "股东"
    },
    {
      "title_hierarchy": [
        "首次公开发行股票并在创业板上市行股票并在",
        "4、新增股东股份锁定承诺"
      ],
      "content": [
        "作为申报前12 个月内的新增股东，黄山佳捷承诺自取得股份之日起 36个月内或本次发行上市之日起 12个月内（以上述期限孰长者为准）不对外转让股份，具体详见本招股说明书“第十二节 附件”之“四、本次发行相关主体作出的重要承诺”之“（一）股份流通限制及自愿锁定的承诺”。"
      ],
      "matched_keyword": "股东"
    },
    {
      "title_hierarchy": [
        "首次公开发行股票并在创业板上市行股票并在",
        "（六）本次发行前各股东之间的关联关系及关联股东的各自持股比例"
      ],
      "content": [
        "本次发行前，公司股东张俊武为黄山佳捷的普通合伙人，持有黄山佳捷 14%的份额；公司股东周斌为黄山佳捷的有限合伙人，持有黄山佳捷 7%的份额。",
        "除上述情况外，截至本招股说明书签署日，发行人各股东之间不存在关联关系。"
      ],
      "matched_keyword": "股东"
    },
    {
      "title_hierarchy": [
        "首次公开发行股票并在创业板上市行股票并在",
        "（七）发行人股东公开发售股份情况"
      ],
      "content": [
        "本次发行不存在发行人股东公开发售股份的情况。"
      ],
      "matched_keyword": "股东"
    },
    {
      "title_hierarchy": [
        "首次公开发行股票并在创业板上市行股票并在",
        "（八）私募投资基金股东备案登记情况"
      ],
      "content": [
        "截至本招股说明书签署日，公司共有股东 6名，其中自然人股东 2名，机构股东4名。上述机构股东不存在以非公开方式向投资者募集资金设立的情形，亦不存在委托其他管理机构管理资产的情形或行为，不属于私募投资基金或私募投资基金管理人，不需履行私募投资基金管理人登记或私募投资基金备案程序。"
      ],
      "matched_keyword": "股东"
    },
    {
      "title_hierarchy": [
        "首次公开发行股票并在创业板上市行股票并在",
        "（九）契约型基金、资产管理计划或信托计划持股情况"
      ],
      "content": [
        "截至本招股说明书签署日，公司股东不存在契约型基金、资产管理计划或信托计划等情形。"
      ],
      "matched_keyword": "股东"
    },
    {
      "title_hierarchy": [
        "首次公开发行股票并在创业板上市行股票并在",
        "1、对赌协议基本情况"
      ],
      "content": [
        "2021年9月18 日，赛格高技术、上汽科技与谷捷有限及原股东黄山供销集团、张俊武、周斌签署《黄山谷捷散热科技有限公司增资协议》（以下简称“增资协议”），对回购条款、继续增资权、责任条款、恢复条款等特殊权利进行了约定，具体如下：",
        "![](images/34c1180f8a1c838a12ca9f6c30258e2fb3d85f005cab209e44848e0cee8a7e87.jpg)",
        "![](images/5bdf7e6fb845ca87cf2a375542cbb01dd440934ddcee8c0c5e76e5644e8082d2.jpg)"
      ],
      "matched_keyword": "增资"
    },
    {
      "title_hierarchy": [
        "首次公开发行股票并在创业板上市行股票并在",
        "2、对赌协议终止情况"
      ],
      "content": [
        "2021 年 12 月 16 日，赛格高技术、上汽科技与谷捷有限及原股东黄山供销集团、张俊武、周斌签署了《黄山谷捷散热科技有限公司增资协议之补充协议》，约定自该补充协议签署之日起，《增资协议》中关于股东退出、继续增资权等涉及公司承担对赌义务的相关条款（包括但不限于《增资协议》第二条 2.4款，第十三条第 13.2 款，第十九条 19.1 款、19.6 款），其中涉及公司作为对赌义务人的相关内容自动终止且自始无效，公司不再承担对赌义务/责任。",
        "2023年3月28日，赛格高技术、上汽科技与发行人及原股东黄山供销集团、张俊武、周斌签署了《黄山谷捷散热科技有限公司增资协议之补充协议（二）》，约定：自该补充协议签署生效之日起，《增资协议》中关于继续增资权、股权转让等特殊权利条款中公司原股东需承担义务/责任的相关内容，包括但不限于《增资协议》第二条 2.4 款，第八条 8.5 款、8.7 款、8.9 款，第十二条 12.1 款、12.2款，第十九条 19.1 款、19.6 款，自动终止且自始无效，公司原股东均不再承担相关的义务/责任；《增资协议》第十三条 13.2款涉及公司原股东承担对赌义务/责任的内容，自公司向证券监管机构提交上市申报材料时效力终止。如公司因撤回上市申请或上市申请被否决而未完成上市，自撤回之日或否决之日起，上述条款中涉及公司原股东承担对赌义务/责任的内容自动恢复效力，投资方有权要求公司原股东承担对赌义务/责任；自该补充协议签署生效之日起，《增资协议》中关于一致同意事项、股东知情权等特殊权利条款中公司需承担义务/责任的相关内容，包括但不限于《增资协议》第八条 8.5 款、8.7 款、8.9 款，第十二条 12.2款，第十九条 19.1 款、19.6 款，自动终止且自始无效，公司均不再承担相关的义务/责任。",
        "2023年9月15日，赛格高技术、上汽科技与发行人及原股东黄山供销集团、张俊武、周斌签署了《黄山谷捷散热科技有限公司增资协议之补充协议（三）》，约定《增资协议之补充协议（二）》第 1.3 条彻底终止且自始无效，同时《增资协议》第十三条 13.2 款涉及公司原股东承担对赌义务/责任的内容，自动终止且自始无效，公司原股东不再承担相关的义务/责任。",
        "2023年9月15 日，赛格高技术、上汽科技、黄山供销集团、张俊武、周斌出具确认暨承诺函如下：",
        "（1）截至本函出具日，不存在触发对赌协议生效的情形，未曾实际执行过对赌条款或提出过回购要求。",
        "（2）本企业/本人确认《增资协议》中关于回购条款、继续增资权等涉及公司及公司原股东承担对赌义务的相关条款，包括但不限于《增资协议》第二条2.4 款，第八条 8.5 款、8.7 款、8.9 款，第十二条 12.1 款、12.2 款，第十三条 13.2款，第十九条 19.1 款、19.6 款，自动终止且自始无效，对公司及公司原股东不再具有法律效力，公司及公司原股东不再承担相关义务/责任，各方不存在任何权利主张、争议及潜在纠纷。",
        "综上，发行人历史上的对赌条款均已清理完毕，相关入股或增资协议中涉及的特殊权利条款不存在触发或执行的情形。"
      ],
      "matched_keyword": "增资"
    },
    {
      "title_hierarchy": [
        "首次公开发行股票并在创业板上市行股票并在",
        "（十一）本次发行前穿透计算股东人数情况"
      ],
      "content": [
        "本次发行前，公司共有 6名股东，按照穿透计算的相关规定，公司经穿透核查后的实际持股人数不超过 200人。"
      ],
      "matched_keyword": "股东"
    },
    {
      "title_hierarchy": [
        "首次公开发行股票并在创业板上市行股票并在",
        "1、董事、监事、高级管理人员及其他核心人员的薪酬组成、确定依据及所履行的程序"
      ],
      "content": [
        "报告期内，在公司专职的董事、监事，按照其在公司实际担任的职务与岗位责任确定薪酬标准，不再另行领取董事或者监事津贴。不在公司专职的非独立董事和监事，不在公司领取薪酬，不享受津贴或福利待遇。独立董事实行固定津贴制度，具体津贴标准由董事会薪酬与考核委员会拟定，并经董事会审议通过后提交股东大会批准。",
        "公司高级管理人员及其他核心人员的薪酬由基本薪酬和绩效薪酬组成。其中，基本薪酬主要依据职位、责任、能力、市场薪资行情等因素确定，绩效薪酬根据公司每年实现效益情况以及高级管理人员和其他核心人员的工作业绩核定。",
        "发行人根据规定设立董事会薪酬与考核委员会，负责制定公司董事及高级管理人员的薪酬标准与考核方案及管理。发行人董事、监事、高级管理人员及其他核心人员的薪酬和考核情况均经发行人履行相关决策程序审议确定。"
      ],
      "matched_keyword": "股东"
    },
    {
      "title_hierarchy": [
        "首次公开发行股票并在创业板上市行股票并在",
        "1、实施股权激励的背景及人员构成"
      ],
      "content": [
        "2022 年 5 月，公司设立员工持股平台黄山佳捷实施股权激励，由黄山佳捷向公司增资，通过黄山佳捷间接持有公司股份的人员均为公司中高层管理人员及骨干员工，具体情况见本节之“二、发行人的设立情况、报告期内的股本和股东变化情况”之“（二）发行人报告期内的股本和股东变化情况”之“5、2022年5月，第二次增资，增资至 1,804.5113万元”。"
      ],
      "matched_keyword": "增资"
    },
    {
      "title_hierarchy": [
        "首次公开发行股票并在创业板上市行股票并在",
        "2、公司员工持股平台基本情况"
      ],
      "content": [
        "截至本招股说明书签署日，包括张俊武、周斌等在内的 15 名员工通过黄山佳捷持有公司 300 万股，持股比例为 5%，黄山佳捷的基本情况见本节之“七、持有发行人 5%以上股份或表决权的主要股东及实际控制人情况”之“（三）其他持有发行人 5%以上股份或表决权的主要股东的基本情况”之“3、黄山佳捷股权管理中心（有限合伙）”。"
      ],
      "matched_keyword": "股东"
    },
    {
      "title_hierarchy": [
        "首次公开发行股票并在创业板上市行股票并在",
        "2、股权激励对财务状况的影响"
      ],
      "content": [
        "2022年4月28日，中联国信出具《资产评估报告》（皖中联国信评报字（2022）第 171 号），确认截至 2021 年 12 月 31 日，谷捷有限股东全部权益的市场价值为 40,370.00 万元。员工持股平台黄山佳捷增资的价格以上述评估价值为基准，确定为23.55元/注册资本。",
        "本次股权激励的增资价格以资产评估结果为基准确定，亦不低于最近一次外部投资者赛格高技术与上汽科技 2021年11 月的增资价格22.42元/注册资本；本次股权激励按 2021 年经审计归属于母公司的扣除非经常性损益后的净利润计算，增资价格对应市盈率为 11.88倍。",
        "本次股权激励的增资价格公允，不涉及为获取职工或其他方的服务而以低于公允价值的交易价格授予员工股权的情形，不涉及股份支付，对公司财务状况无重大影响。"
      ],
      "matched_keyword": "增资"
    },
    {
      "title_hierarchy": [
        "首次公开发行股票并在创业板上市行股票并在",
        "3、股权激励对公司控制权的影响"
      ],
      "content": [
        "股权激励实施完毕后，公司控股股东、实际控制人未发生变化，股权激励不会影响公司控制权。"
      ],
      "matched_keyword": "股东"
    },
    {
      "title_hierarchy": [
        "首次公开发行股票并在创业板上市行股票并在",
        "3、控股股东关于社会保险、住房公积金事项的承诺"
      ],
      "content": [
        "发行人控股股东黄山供销集团已出具承诺，详见“第十二节 附件”之“四、",
        "本次发行相关主体作出的重要承诺”之“（十一）其他承诺事项”"
      ],
      "matched_keyword": "股东"
    },
    {
      "title_hierarchy": [
        "首次公开发行股票并在创业板上市行股票并在",
        "3、前五大客户中新增客户情况"
      ],
      "content": [
        "报告期内，博世、斯达半导及黄山方平铜业有限公司、上汽英飞凌和浙江卓昌金属有限公司及郎溪联合铜业有限公司分别在 2021 年、2022 年、2023 年和2024年1-6月成为公司营业收入前五大客户。",
        "前五大客户中新增客户的基本情况如下：",
        "![](images/42789fa5deaa5b5b8ba882df1db95d66a87b0a86ec4c1d56f5c14948a7fc7fe0.jpg)",
        "前五大客户中新增客户报告期销售额如下：",
        "单位：万元",
        "![](images/2f9ab737e0b259ee478d75bb3114a08d6906220548a9d79a9a6970d8c4d2ab36.jpg)",
        "如上表，博世和斯达半导均为发行人长期合作客户，报告期内，受益于新能源汽车终端需求旺盛，两者作为知名车规级功率模块制造商，向发行人大量采购散热基板，成为发行人前五大客户。上汽英飞凌由上汽集团与英飞凌合资设立，为进一步发挥上汽英飞凌本土化服务的优势，上汽英飞凌负责供应的国内市场功率半导体产品逐步增加，成为发行人前五大客户。同时，由于报告期发行人规模不断扩张，生产过程中产生的铜废料量快速增长，发行人通过商务洽谈的方式，经询价比较后与多家铜废料收购方达成合作，黄山方平铜业有限公司、浙江卓昌金属有限公司和郎溪联合铜业有限公司成为发行人前五大客户。",
        "2022年、2023 年和2024年1-6月，部分客户退出前五大，主要是随着公司的销售规模增长、新客户的开发，部分客户销售占比相应减少。日本悠年 2022年起退出发行人主营业务收入前五大客户，主要原因系日本悠年下游客户需求减少导致其向发行人的采购量下降，发行人目前仍与日本悠年保持良好合作关系，2023 年销售收入 386.31 万元。中车时代 2023 年退出发行人营业收入前五大客户，但仍为发行人前十大客户。上汽英飞凌 2024 年 1-6 月退出发行人营业收入前五大客户，但仍与发行人保持稳定合作。此外，随着发行人铜废料销售量的增加，经比价竞争，发行人与多家收购方达成合作，宣城市富旺金属材料有限公司报价未达标准，2023年发行人不再与其合作；黄山方平铜业有限公司 2023 年度退出发行人前五大客户，但仍与发行人保持稳定合作。",
        "报告期内，公司与前五大客户之间不存在关联关系，公司董事、监事、高级管理人员、其他核心人员、持有发行人 5%股份以上的股东未在上述客户中拥有权益。"
      ],
      "matched_keyword": "股东"
    },
    {
      "title_hierarchy": [
        "首次公开发行股票并在创业板上市行股票并在",
        "2、前五大供应商中新增供应商情况"
      ],
      "content": [
        "报告期内，宁波金田电材有限公司和上海广弘实业有限公司分别在 2021 年和2022年成为公司前五大供应商。",
        "前五大供应商中新增供应商的基本情况及原因如下：",
        "![](images/9b390482f820e3401fba5ad258fcb6827ce7af36627302346dd7e60ca643294a.jpg)",
        "前五大供应商中新增供应商报告期采购额如下：",
        "单位：万元",
        "![](images/d6c2c7e24a814d40c31825a8c83ee4ef5657e9c52c4fae85fefc0191cac3f4c3.jpg)",
        "报告期内，公司董事、监事、高级管理人员、其他核心人员、持有发行人5%股份以上的股东未在上述供应商中拥有权益。"
      ],
      "matched_keyword": "股东"
    },
    {
      "title_hierarchy": [
        "首次公开发行股票并在创业板上市行股票并在",
        "第六节 财务会计信息与管理层分析"
      ],
      "content": [
        "公司聘请中审众环会计师对公司截至 2021 年 12 月 31 日、2022 年 12 月 31日、2023 年 12 月 31 日和 2024 年 6 月 30 日的合并及公司资产负债表， 2021 年度、2022年度、2023 年度和2024年1-6月的合并及公司利润表、合并及公司现金流量表和合并及公司股东权益变动表以及相关财务报表附注进行了审计，并出具了标准无保留意见的《审计报告》（众环审字（2024）0104198 号）。本节引用的财务会计数据除特别说明外，均引自经审计的财务报告且为合并财务报表口径。",
        "公司提请投资者注意，投资者欲对公司的财务状况、经营成果和现金流量等进行更详细的了解，还应阅读财务报告及审计报告全文，以获取全面的财务资料。",
        "本节的财务会计数据及有关分析说明反映了公司报告期内经审计的财务状况、经营成果和现金流量情况。管理层讨论分析部分采用了结合公司经营模式特点以及与同行业公司对比分析的方法，以便投资者更深入理解公司的财务及非财务信息。可比公司的相关信息均来自其公开披露资料。"
      ],
      "matched_keyword": "股东"
    },
    {
      "title_hierarchy": [
        "首次公开发行股票并在创业板上市行股票并在",
        "1、影响公司盈利能力的主要财务指标"
      ],
      "content": [
        "根据公司所处的行业状况及自身业务特点，公司主营业务收入增长率、归属于母公司股东的净利润增长率等财务指标对分析公司的收入、成本、费用和利润具有较为重要意义，其变动对公司业绩波动具有较强的预示作用。"
      ],
      "matched_keyword": "股东"
    },
    {
      "title_hierarchy": [
        "首次公开发行股票并在创业板上市行股票并在",
        "（2）归属于母公司股东的净利润增长率"
      ],
      "content": [
        "报告期内，公司归属于母公司股东的净利润分别为 3,427.86 万元、9,947.19万元、15,728.32 万元和 6,059.75 万元，2021-2023 年年均复合增长率为 114.21%。报告期内，公司归属于母公司股东的净利润快速增长，公司具有稳定持续的盈利",
        "能力。"
      ],
      "matched_keyword": "股东"
    },
    {
      "title_hierarchy": [
        "首次公开发行股票并在创业板上市行股票并在",
        "2、合并财务报表编制的方法"
      ],
      "content": [
        "从取得子公司的净资产和生产经营决策的实际控制权之日起，本公司开始将其纳入合并范围；从丧失实际控制权之日起停止纳入合并范围。对于处置的子公司，处置日前的经营成果和现金流量已经适当地包括在合并利润表和合并现金流量表中；当期处置的子公司，不调整合并资产负债表的期初数。非同一控制下企业合并增加的子公司，其购买日后的经营成果及现金流量已经适当地包括在合并利润表和合并现金流量表中，且不调整合并财务报表的期初数和对比数。同一控制下企业合并增加的子公司及吸收合并下的被合并方，其自合并当期期初至合并日的经营成果和现金流量已经适当地包括在合并利润表和合并现金流量表中，并且同时调整合并财务报表的对比数。",
        "在编制合并财务报表时，子公司与本公司采用的会计政策或会计期间不一致的，按照本公司的会计政策和会计期间对子公司财务报表进行必要的调整。对于非同一控制下企业合并取得的子公司，以购买日可辨认净资产公允价值为基础对其财务报表进行调整。",
        "公司内所有重大往来余额、交易及未实现利润在合并财务报表编制时予以抵销。",
        "子公司的股东权益及当期净损益中不属于本公司所拥有的部分分别作为少数股东权益及少数股东损益在合并财务报表中股东权益及净利润项下单独列示。子公司当期净损益中属于少数股东权益的份额，在合并利润表中净利润项目下以“少数股东损益”项目列示。少数股东分担的子公司的亏损超过了少数股东在该子公司期初股东权益中所享有的份额，仍冲减少数股东权益。",
        "当因处置部分股权投资或其他原因丧失了对原有子公司的控制权时，对于剩余股权，按照其在丧失控制权日的公允价值进行重新计量。处置股权取得的对价与剩余股权公允价值之和，减去按原持股比例计算应享有原有子公司自购买日开始持续计算的净资产的份额之间的差额，计入丧失控制权当期的投资收益。与原有子公司股权投资相关的其他综合收益，在丧失控制权时采用与该子公司直接处置相关资产或负债相同的基础进行会计处理。其后，对该部分剩余股权按照《企业会计准则第 2 号— 长期股权投资》或《企业会计准则第 22 号——金融工具确认和计量》等相关规定进行后续计量，详见“（九）长期股权投资”或“（五）金融工具”。",
        "本公司通过多次交易分步处置对子公司股权投资直至丧失控制权的，需区分处置对子公司股权投资直至丧失控制权的各项交易是否属于一揽子交易。处置对子公司股权投资的各项交易的条款、条件以及经济影响符合以下一种或多种情况，通常表明应将多次交易事项作为一揽子交易进行会计处理：①这些交易是同时或者在考虑了彼此影响的情况下订立的；②这些交易整体才能达成一项完整的商业结果；③一项交易的发生取决于其他至少一项交易的发生；④一项交易单独看是不经济的，但是和其他交易一并考虑时是经济的。不属于一揽子交易的，对其中的每一项交易视情况分别按照“不丧失控制权的情况下部分处置对子公司的长期股权投资”（详见“（九）长期股权投资”之2、④）和“因处置部分股权投资或其他原因丧失了对原有子公司的控制权”（详见前段）适用的原则进行会计处理。处置对子公司股权投资直至丧失控制权的各项交易属于一揽子交易的，将各项交易作为一项处置子公司并丧失控制权的交易进行会计处理；但是，在丧失控制权之前每一次处置价款与处置投资对应的享有该子公司净资产份额的差额，在合并财务报表中确认为其他综合收益，在丧失控制权时一并转入丧失控制权当期的损益。"
      ],
      "matched_keyword": "股东"
    },
    {
      "title_hierarchy": [
        "首次公开发行股票并在创业板上市行股票并在",
        "③收购少数股权"
      ],
      "content": [
        "在编制合并财务报表时，因购买少数股权新增的长期股权投资与按照新增持股比例计算应享有子公司自购买日（或合并日）开始持续计算的净资产份额之间的差额，调整资本公积，资本公积不足冲减的，调整留存收益。"
      ],
      "matched_keyword": "持股比例"
    },
    {
      "title_hierarchy": [
        "首次公开发行股票并在创业板上市行股票并在",
        "④处置长期股权投资"
      ],
      "content": [
        "在合并财务报表中，母公司在不丧失控制权的情况下部分处置对子公司的长期股权投资，处置价款与处置长期股权投资相对应享有子公司净资产的差额计入股东权益；母公司部分处置对子公司的长期股权投资导致丧失对子公司控制权的，按“（二）合并财务报表的编制方法”之“2、合并财务报表编制的方法”中所述的相关会计政策处理。",
        "其他情形下的长期股权投资处置，对于处置的股权，其账面价值与实际取得价款的差额，计入当期损益。",
        "采用权益法核算的长期股权投资，处置后的剩余股权仍采用权益法核算的，在处置时将原计入股东权益的其他综合收益部分按相应的比例采用与被投资单位直接处置相关资产或负债相同的基础进行会计处理。因被投资方除净损益、其他综合收益和利润分配以外的其他所有者权益变动而确认的所有者权益，按比例结转入当期损益。",
        "采用成本法核算的长期股权投资，处置后剩余股权仍采用成本法核算的，其在取得对被投资单位的控制之前因采用权益法核算或金融工具确认和计量准则核算而确认的其他综合收益，采用与被投资单位直接处置相关资产或负债相同的基础进行会计处理，并按比例结转当期损益；因采用权益法核算而确认的被投资单位净资产中除净损益、其他综合收益和利润分配以外的其他所有者权益变动按",
        "比例结转当期损益。"
      ],
      "matched_keyword": "股东"
    },
    {
      "title_hierarchy": [
        "首次公开发行股票并在创业板上市行股票并在",
        "（十五）收入确认原则和计量方法"
      ],
      "content": [
        "收入，是本公司在日常活动中形成的、会导致股东权益增加的、与股东投入资本无关的经济利益的总流入。本公司与客户之间的合同同时满足下列条件时，在客户取得相关商品（含劳务，下同）控制权时确认收入：合同各方已批准该合同并承诺将履行各自义务；合同明确了合同各方与所转让商品或提供劳务相关的权利和义务；合同有明确的与所转让商品相关的支付条款；合同具有商业实质，即履行该合同将改变本公司未来现金流量的风险、时间分布或金额；本公司因向客户转让商品而有权取得的对价很可能收回。其中，取得相关商品控制权，是指能够主导该商品的使用并从中获得几乎全部的经济利益。",
        "在合同开始日，本公司识别合同中存在的各单项履约义务，并将交易价格按照各单项履约义务所承诺商品的单独售价的相对比例分摊至各单项履约义务。在确定交易价格时考虑了可变对价、合同中存在的重大融资成分、非现金对价、应付客户对价等因素的影响。",
        "对于合同中的每个单项履约义务，如果满足下列条件之一的，本公司在相关履约时段内按照履约进度将分摊至该单项履约义务的交易价格确认为收入：客户在本公司履约的同时即取得并消耗本公司履约所带来的经济利益；客户能够控制本公司履约过程中在建的商品；本公司履约过程中所产出的商品具有不可替代用途，且本公司在整个合同期间内有权就累计至今已完成的履约部分收取款项。履约进度根据所转让商品的性质采用投入法或产出法确定，当履约进度不能合理确定时，本公司已经发生的成本预计能够得到补偿的，按照已经发生的成本金额确认收入，直到履约进度能够合理确定为止。",
        "如果不满足上述条件之一，则本公司在客户取得相关商品控制权的时点按照分摊至该单项履约义务的交易价格确认收入。在判断客户是否已取得商品控制权时，本公司考虑下列迹象：企业就该商品享有现时收款权利，即客户就该商品负有现时付款义务；企业已将该商品的法定所有权转移给客户，即客户已拥有该商品的法定所有权；企业已将该商品实物转移给客户，即客户已实物占有该商品；企业已将该商品所有权上的主要风险和报酬转移给客户，即客户已取得该商品所有权上的主要风险和报酬；客户已接受该商品；其他表明客户已取得商品控制权的迹象。"
      ],
      "matched_keyword": "股东"
    },
    {
      "title_hierarchy": [
        "首次公开发行股票并在创业板上市行股票并在",
        "3、所得税费用"
      ],
      "content": [
        "所得税费用包括当期所得税和递延所得税。",
        "除确认为其他综合收益或直接计入股东权益的交易和事项相关的当期所得税和递延所得税计入其他综合收益或股东权益，以及企业合并产生的递延所得税调整商誉的账面价值外，其余当期所得税和递延所得税费用或收益计入当期损益。"
      ],
      "matched_keyword": "股东"
    },
    {
      "title_hierarchy": [
        "首次公开发行股票并在创业板上市行股票并在",
        "七、非经常性损益"
      ],
      "content": [
        "中审众环会计师审核了公司报告期内的非经常性损益明细表，出具了《关于黄山谷捷股份有限公司非经常性损益的鉴证报告》（众环专字（2024）0101419号），公司报告期内发生的非经常性损益情况如下表：",
        "单位：万元",
        "![](images/4058940a705d5028ed5dfaa676e04c8a13761f0ec92c8b5e8bf5242fb6d618a0.jpg)",
        "报告期内，公司归属于发行人股东的非经常性损益占归属于发行人股东净利润的比例分别为 0.86%、2.77%、7.62%和 13.83%，非经常性损益对公司经营成",
        "果影响较小。"
      ],
      "matched_keyword": "股东"
    },
    {
      "title_hierarchy": [
        "首次公开发行股票并在创业板上市行股票并在",
        "（一）基本财务指标"
      ],
      "content": [
        "![](images/0684131d2e5e30a662dd25484c5492285e1d83a36d48ede0adfd802b3700aadf.jpg)",
        "注：流动比率＝流动资产÷流动负债",
        "速动比率＝（流动资产-存货净额）÷流动负债",
        "资产负债率＝（负债总额÷资产总额）×100%",
        "归属于发行人股东的每股净资产=归属于发行人股东的所有者权益÷年末股本总数",
        "应收账款周转率＝营业收入÷应收账款期初期末平均余额",
        "存货周转率=营业成本÷存货期初期末平均余额",
        "息税折旧摊销前利润＝利润总额+利息支出+固定资产折旧+长期待摊费用摊销+无形资 产摊销",
        "利息保障倍数=（利润总额+利息支出）/利息支出",
        "研发费用占营业收入的比例=当期研发费用÷当期营业收入每股经营活动产生的现金流量＝经营活动产生的现金流量净额÷期末普通股总数每股净现金流量＝现金及现金等价物净增加额÷期末普通股总数"
      ],
      "matched_keyword": "股东"
    },
    {
      "title_hierarchy": [
        "首次公开发行股票并在创业板上市行股票并在",
        "注：1、加权平均净资产收益率"
      ],
      "content": [
        "加权平均净资产收益率=P0/（E0＋NP/2＋Ei×Mi/M0–Ej×Mj/M0±Ek×Mk/M0），其中：P0 分别对应于归属于公司普通股股东的净利润、扣除非经常性损益后归属于公司普通股股东的净利润；NP 为归属于公司普通股股东的净利润；E0 为归属于公司普通股股东的期初净资产；Ei 为报告期发行新股或债转股等新增的、归属于公司普通股股东的净资产；Ej 为报告期回购或现金分红等减少的、归属于公司普通股股东的净资产；M0 为报告期月份数；Mi为新增净资产次月起至报告期期末的累计月数；Mj 为减少净资产次月起至报告期期末的累计月数；Ek 为因其他交易或事项引起的、归属于公司普通股股东的净资产增减变动；Mk为发生其他净资产增减变动次月起至报告期期末的累计月数。"
      ],
      "matched_keyword": "股东"
    },
    {
      "title_hierarchy": [
        "首次公开发行股票并在创业板上市行股票并在",
        "S=S0+S1+Si×Mi/M0-Sj×Mj/M0-Sk"
      ],
      "content": [
        "其中：P0 为归属于公司普通股股东的净利润或扣除非经常性损益后归属于普通股股东的净利润；S 为发行在外的普通股加权平均数；S0 为期初股份总数；S1 为报告期因公积金转增股本或股票股利分配等增加股份数；Si 为报告期因发行新股或债转股等增加股份数；Sj 为报告期因回购等减少股份数；Sk 为报告期缩股数；M0 报告期月份数；Mi 为增加股份次月起至报告期期末的累计月数；Mj为减少股份次月起至报告期期末的累计月数。"
      ],
      "matched_keyword": "股东"
    },
    {
      "title_hierarchy": [
        "首次公开发行股票并在创业板上市行股票并在",
        "3、稀释每股收益"
      ],
      "content": [
        "稀释每股收益=P1/（S0+S1+Si×Mi/M0-Sj×Mj/M0-Sk+认股权证、股份期权、可转换债券等增加的普通股加权平均数）",
        "其中，P1 为归属于公司普通股股东的净利润或扣除非经常性损益后归属于公司普通股股东的净利润，并考虑稀释性潜在普通股对其影响，按《企业会计准则》及有关规定进行调整。公司在计算稀释每股收益时，应考虑所有稀释性潜在普通股对归属于公司普通股股东的净利润或扣除非经常性损益后归属于公司普通股股东的净利润和加权平均股数的影响，按照其稀释程度从大到小的顺序计入稀释每股收益，直至稀释每股收益达到最小值。"
      ],
      "matched_keyword": "股东"
    },
    {
      "title_hierarchy": [
        "首次公开发行股票并在创业板上市行股票并在",
        "（2）公司主营业务成本按成本性质列示"
      ],
      "content": [
        "报告期内，公司主营业务成本按照成本性质列示情况如下：",
        "单位：万元",
        "![](images/3187246a1975eadb00bfcf042d7f01a5ac621de1930171d223490b170eb722da.jpg)",
        "![](images/c70f171ede0b4cfd8d69815522f9e43d64bcab0e2b6f29215b2aeb3e681927cb.jpg)",
        "公司主营业务成本由直接材料、直接人工、制造费用、外协加工费和运费组成。直接材料主要为铜排、铜板等，制造费用主要为资产折旧费、水电费、包装材料、刀具等，外协加工费系公司部分产品的委外电镀加工费用。",
        "报告期内，公司主营业务成本结构总体较为稳定，直接材料是公司生产成本的主要构成部分，主要由铜排、铜板等构成。报告期内，直接材料占当期主营业务成本的比例分别为 64.82%、65.98%、68.71%和 67.45%。报告期内，公司的外协加工费分别为 1,594.01 万元、1,971.64 万元、1,817.18 万元和 965.24 万元，占当期主营业务成本的比例分别为 11.40%、7.24%、4.76%和 6.65%。2022 年度及2023 年度外协加工费占比下降，主要系公司增资控股黄山广捷，降低了电镀外协加工采购比例。"
      ],
      "matched_keyword": "增资"
    },
    {
      "title_hierarchy": [
        "首次公开发行股票并在创业板上市行股票并在",
        "1、长期股权投资"
      ],
      "content": [
        "报告期各期末，公司长期股权投资的构成如下：",
        "单位：万元",
        "![](images/ab1412427350d1e1704fc82ceaa58ca7d031241ca851f33ed555685e8ebdbfbc.jpg)",
        "2021 年末，公司长期股权投资金额为 142.72 万元，占非流动资产的比例为",
        "3.16%。2020年3月，公司与上海广弘共同投资设立了黄山广捷，黄山广捷成立之初为发行人持股比例 45%的参股公司。2022 年 5 月，公司通过增资的方式取得了黄山广捷的控制权，持股比例为 51%，黄山广捷成为公司控股子公司。"
      ],
      "matched_keyword": "增资"
    },
    {
      "title_hierarchy": [
        "首次公开发行股票并在创业板上市行股票并在",
        "6、商誉"
      ],
      "content": [
        "报告期各期末，公司商誉情况如下：",
        "单位：万元",
        "![](images/d903d28348808277153d365154eb18abe2223ec0fa5a903d07cfa9c87b2f8426.jpg)",
        "2022 年 5 月，公司因增资取得对黄山广捷的控制权，在购买日之前持有的股权在购买日的公允价值与追加投资款项形成的合并成本为 445.81 万元，取得的子公司可辨认净资产公允价值份额 437.25 万元，形成商誉 8.56 万元。报告期期末，经测试，公司的商誉未发生减值，无需计提商誉减值准备。"
      ],
      "matched_keyword": "增资"
    },
    {
      "title_hierarchy": [
        "首次公开发行股票并在创业板上市行股票并在",
        "（三）股利分配情况"
      ],
      "content": [
        "2021年12月22 日，公司临时股东会审议通过对公司2021年增资扩股前的过渡期利润进行分配的事项。根据2021年 9月18日各股东签署的《黄山谷捷散热科技有限公司增资协议》4.4 条约定“[过渡期损益]各方确认，黄山谷捷过渡期损益全部由原股东承担和享有”，公司将过渡期净利润 19,281,653.11 元按增资前的原股东出资比例进行分配。",
        "2022 年 10 月 28 日，公司 2022 年第一次临时股东大会审议通过了《关于公司利润分配的议案》，公司以总股本 60,000,000 股为基数，向全体股东按每 10股派发现金红利2.50 元（含税），共计派发现金红利 15,000,000.00 元（含税）。",
        "截至本招股说明书签署日，上述股利分配已实施完毕，公司不存在尚未实施完毕的利润分配方案。"
      ],
      "matched_keyword": "增资"
    },
    {
      "title_hierarchy": [
        "首次公开发行股票并在创业板上市行股票并在",
        "3、筹资活动现金流量分析"
      ],
      "content": [
        "报告期内，公司筹资活动产生的现金流量具体情况如下：",
        "单位：万元",
        "![](images/c5fc4e9dbf96d1258399d0714c2176bf843029374eb28a1e6dc9d6866792d940.jpg)",
        "报告期内，公司筹资活动产生的现金流量净额分别为9,395.06万元、-1,686.24万元、616.43 万元和-440.51 万元。2021 年度筹资活动产生的现金流量净额变动较大，主要系公司收到赛格高技术及上汽科技的增资款 11,528.57 万元，同时，为改善资本结构偿还银行借款 6,200.00万元。"
      ],
      "matched_keyword": "增资"
    },
    {
      "title_hierarchy": [
        "首次公开发行股票并在创业板上市行股票并在",
        "2、合并利润表主要数据"
      ],
      "content": [
        "单位：万元",
        "![](images/5e556beaa040c4cbf77cb961c230cff0ffa954d31bacfd7a32ed10430e42a33b.jpg)",
        "2024 年 1-9 月公司营业收入为 48,201.72 万元，较上年同期下降 13.80%；扣除非经常性损益后归属于母公司股东的净利润为 8,113.14 万元，较上年同期下降22.73%，主要受国外新能源汽车政策放缓、新能源汽车价格战向上游传导以及铜价上涨的影响。"
      ],
      "matched_keyword": "股东"
    },
    {
      "title_hierarchy": [
        "首次公开发行股票并在创业板上市行股票并在",
        "（一）本次募集资金金额及投资项目"
      ],
      "content": [
        "根据发行人于 2023年2月2日召开的 2023年第一次临时股东大会决议，本次发行募集资金扣除发行费用后，将用于以下项目：",
        "单位：万元",
        "![](images/ded911dab8af9e725572366b8e04ca30e99e0baf98ff607c44f211714879d8bd.jpg)",
        "如本次发行实际募集资金少于上述拟投资项目的计划募集资金使用量，不足部分将由发行人以自筹资金解决。如本次发行实际募集资金超出上述拟投资项目的计划募集资金使用量，超出部分将全部用于其他与主营业务相关的项目。如本次募集资金到位前，发行人使用自筹资金对拟投资项目进行先期投入的，待本次募集资金到位后将予以置换。"
      ],
      "matched_keyword": "股东"
    },
    {
      "title_hierarchy": [
        "首次公开发行股票并在创业板上市行股票并在",
        "一、报告期内公司治理存在的缺陷及改进情况"
      ],
      "content": [
        "报告期内，公司根据《公司法》和《公司章程》的规定，参照上市公司的要求，先后审议通过了《股东大会议事规则》《董事会议事规则》《监事会议事规则》《总经理工作细则》《独立董事工作制度》《董事会秘书工作制度》等一系列规章制度，设立了战略委员会、审计委员会、提名委员会、薪酬与考核委员会，形成了权力机构、决策机构、监督机构和管理层之间运作规范、权责明确的治理机制。通过对上述规章制度的制定和机构的建立，公司逐步建立健全了符合上市要求的、能够保证中小股东充分行使权利的公司治理结构。",
        "自股份公司设立以来，公司股东大会、董事会、监事会、管理层、独立董事之间权责明确，按照相关法律法规及规范性文件、《公司章程》及相关议事规则的要求规范运行，各股东、董事、监事和高级管理人员均尽职尽责，按制度规定切实地行使权利、履行义务，未发生违法违规情形。报告期内，公司治理规范，不存在重大缺陷。"
      ],
      "matched_keyword": "股东"
    },
    {
      "title_hierarchy": [
        "首次公开发行股票并在创业板上市行股票并在",
        "四、发行人报告期内的资金占用和对外担保情况"
      ],
      "content": [
        "报告期内，公司不存在资金被控股股东、实际控制人及其控制的其他企业以借款、代偿债务、代垫款项或其他方式占用的情形，亦不存在为控股股东、实际控制人及其控制的其他企业提供担保的情形。"
      ],
      "matched_keyword": "股东"
    },
    {
      "title_hierarchy": [
        "首次公开发行股票并在创业板上市行股票并在",
        "五、发行人直接面向市场独立持续经营的能力"
      ],
      "content": [
        "自股份公司成立以来，发行人按照《公司法》《证券法》等有关法律、法规和《公司章程》的要求规范运作，建立健全了公司法人治理结构。截至本招股说明书签署日，发行人在资产、人员、财务、机构、业务等方面均独立于控股股东、实际控制人及其控制的其他企业，具有独立、完整的业务体系，具备面向市场独立自主经营的能力。"
      ],
      "matched_keyword": "股东"
    },
    {
      "title_hierarchy": [
        "首次公开发行股票并在创业板上市行股票并在",
        "（一）资产完整"
      ],
      "content": [
        "公司由有限公司整体变更设立，各项资产及负债由公司依法承继。截至本招股说明书签署日，公司具备与生产经营有关的生产系统、辅助生产系统和配套设施，合法拥有与生产经营有关的土地、厂房、机器设备以及商标、专利、非专利技术的所有权或使用权，具有独立完整的采购、生产、销售系统。公司资产完整，独立于控股股东、实际控制人及其控制的其他企业。"
      ],
      "matched_keyword": "股东"
    },
    {
      "title_hierarchy": [
        "首次公开发行股票并在创业板上市行股票并在",
        "（二）人员独立"
      ],
      "content": [
        "公司拥有独立、规范的劳动、人事、薪酬管理体系，与控股股东、实际控制人及其控制的其他企业保持独立。公司总经理、副总经理、财务负责人和董事会秘书等高级管理人员未在控股股东、实际控制人及其控制的其他企业担任除董事、",
        "监事以外其他职务，未在控股股东、实际控制人及其控制的其他企业领薪。发行人的财务人员未在控股股东、实际控制人及其控制的其他企业中兼职。"
      ],
      "matched_keyword": "股东"
    },
    {
      "title_hierarchy": [
        "首次公开发行股票并在创业板上市行股票并在",
        "（三）财务独立"
      ],
      "content": [
        "公司设立了独立的财务部门，配备了专职财务人员，建立了独立的会计核算体系，能够独立作出财务决策，具有较为规范的财务会计制度和对子公司的财务管理制度。公司开设了独立的银行账号，不存在与控股股东、实际控制人及其控制的其他企业共用银行账户的情形。发行人依法独立进行纳税申报并缴纳税金。"
      ],
      "matched_keyword": "股东"
    },
    {
      "title_hierarchy": [
        "首次公开发行股票并在创业板上市行股票并在",
        "（四）机构独立"
      ],
      "content": [
        "发行人已依照《公司法》和《公司章程》设置股东大会、董事会、监事会等决策及监督机构，建立健全符合自身经营情况、独立完整的内部经营管理机构，独立行使经营管理职权，与控股股东和实际控制人及其控制的其他企业间不存在机构混同的情形。"
      ],
      "matched_keyword": "股东"
    },
    {
      "title_hierarchy": [
        "首次公开发行股票并在创业板上市行股票并在",
        "（五）业务独立"
      ],
      "content": [
        "公司具有独立完整的研发、生产、销售体系，与控股股东、实际控制人及其控制的其他企业不存在构成重大不利影响的同业竞争或严重影响发行人独立性或显失公平的关联交易，不存在需要依赖关联方及其他关联方进行经营活动的情况。"
      ],
      "matched_keyword": "股东"
    },
    {
      "title_hierarchy": [
        "首次公开发行股票并在创业板上市行股票并在",
        "（六）主营业务、控制权及管理团队的稳定性"
      ],
      "content": [
        "公司主营业务、控制权、管理团队稳定，最近两年内主营业务和董事、高级管理人员均未发生重大不利变化；控股股东和受控股股东、实际控制人支配的股东所持发行人的股份权属清晰，最近两年实际控制人未发生变更，不存在导致控制权可能变更的重大权属纠纷。"
      ],
      "matched_keyword": "股东"
    },
    {
      "title_hierarchy": [
        "首次公开发行股票并在创业板上市行股票并在",
        "（一）发行人与控股股东、实际控制人及其控制的其他企业不存在同业竞争"
      ],
      "content": [
        "发行人控股股东为黄山供销集团，实际控制人为黄山市供销社，具体情况详见“第四节 发行人基本情况”之“七、持有发行人 5%以上股份或表决权的主要股东及实际控制人情况”之“（一）控股股东及实际控制人的基本情况”。黄山市供销社自身不从事生产经营活动，黄山供销集团主要从事“三农服务”与项目投资，发行人主要从事功率半导体模块散热基板的研发、生产和销售。发行人与控股股东、实际控制人不存在同业竞争。",
        "截至本招股说明书签署日，控股股东、实际控制人控制的企业情况详见“第四节 发行人基本情况”之“七、持有发行人 5%以上股份或表决权的主要股东及实际控制人情况”之“（四）控股股东、实际控制人控制的其他企业”，与发行人不存在同业竞争。",
        "报告期内，黄山供销集团曾经控制的企业昆山谷捷业务范围包括散热器的制造与销售，但报告期内昆山谷捷未实际开展经营活动。2021 年 4 月，谷捷有限吸收合并昆山谷捷，昆山谷捷已注销。",
        "截至本招股说明书签署日，发行人与控股股东、实际控制人及其控制的其他企业不存在同业竞争的情形。"
      ],
      "matched_keyword": "股东"
    },
    {
      "title_hierarchy": [
        "首次公开发行股票并在创业板上市行股票并在",
        "（二）发行人控股股东关于避免同业竞争的承诺"
      ],
      "content": [
        "为有效避免今后可能发生或潜在的同业竞争，发行人控股股东及实际控制人已出具《关于同业竞争事项的承诺》，具体承诺详见“第十二节 附件”之“四、本次发行相关主体作出的重要承诺”之“（十一）其他承诺事项”。"
      ],
      "matched_keyword": "股东"
    },
    {
      "title_hierarchy": [
        "首次公开发行股票并在创业板上市行股票并在",
        "1、控股股东、实际控制人及其他持有公司 5%以上股份的法人"
      ],
      "content": [
        "![](images/f393ade37fcdc3a91e2df47bfae5b036d6657edc824b00b9d59ea8251557df89.jpg)"
      ],
      "matched_keyword": "股东"
    },
    {
      "title_hierarchy": [
        "首次公开发行股票并在创业板上市行股票并在",
        "2、控股股东、实际控制人控制、共同控制或施加重大影响的其他企业"
      ],
      "content": [
        "发行人控股股东、实际控制人控制的除发行人之外的企业情况详见“第四节发行人基本情况”之“七、持有发行人 5%以上股份或表决权的主要股东及实际控制人情况”之“（四）控股股东、实际控制人控制的其他企业”。黄山供销集团及其直接、间接控制企业的合营企业、联营企业数量众多，该等企业均是发行人的关联方。报告期内与发行人发生关联交易或存在关联往来的控股股东、实际控制人控制、共同控制或施加重大影响的企业如下：",
        "![](images/f0465e5651cb0fce718773429fc7f005085a90dcf6395fadd9bd857f91c2f62a.jpg)"
      ],
      "matched_keyword": "股东"
    },
    {
      "title_hierarchy": [
        "首次公开发行股票并在创业板上市行股票并在",
        "（2）发行人董事、监事、高级管理人员及其关系密切的家庭成员"
      ],
      "content": [
        "发行人董事、监事、高级管理人员详见本招股说明书“第四节 发行人基本",
        "情况”之“十二、董事、监事、高级管理人员与其他核心人员”之“（一）董事、监事、高级管理人员及其他核心人员的简介”。",
        "（3）控股股东、实际控制人的董事、监事、高级管理人员及其关系密切的家庭成员",
        "![](images/60d4c3f29ada1754782da62be5195193cda8ce2d5a031956f4896e1d29e70fd5.jpg)",
        "关联自然人关系密切的家庭成员，包括配偶、父母、配偶的父母、兄弟姐妹及其配偶、年满十八周岁的子女及其配偶、配偶的兄弟姐妹和子女配偶的父母。"
      ],
      "matched_keyword": "股东"
    },
    {
      "title_hierarchy": [
        "首次公开发行股票并在创业板上市行股票并在",
        "①关联采购的必要性与合理性"
      ],
      "content": [
        "报告期内，上海广弘与黄山广捷为公司提供电镀加工服务。上海广弘为总部位于上海的一家专业进行金属表面处理加工的生产型企业，自 2018 年起即为公司提供电镀加工服务，为降低交易成本及提高交易便利性，2020 年公司与上海广弘共同投资成立黄山广捷，上海广弘作为黄山广捷的重要股东，基于谨慎性原则，将其认定为公司关联方。电镀加工系公司主营业务的生产工序之一，发行人向关联方采购电镀加工服务满足业务发展及生产经营需要，具有必要性和合理性。"
      ],
      "matched_keyword": "股东"
    },
    {
      "title_hierarchy": [
        "首次公开发行股票并在创业板上市行股票并在",
        "（2）出售商品、提供劳务"
      ],
      "content": [
        "报告期内，持有公司 5%以上股份的股东赛格高技术自身及通过广瑞特、天芯创联、芯辰达从发行人处采购散热基板用于销售，基本情况如下：",
        "![](images/c9d88b722618be6d7fa4ff7fe69fb9ffe19c1116265d747e6ce5fac6c1c93195.jpg)"
      ],
      "matched_keyword": "股东"
    },
    {
      "title_hierarchy": [
        "首次公开发行股票并在创业板上市行股票并在",
        "（三）关联交易决策程序及独立董事意见"
      ],
      "content": [
        "发行人已经建立了完善的公司治理制度，在《公司章程》《股东大会议事规则》《董事会议事规则》《独立董事工作制度》《关联交易管理制度》等制度中对关联交易决策权限、决策程序、回避表决安排等做出了规定，从制度上保证了发行人关联交易决策的公允性，确保关联交易行为不损害发行人和全体股东的利益。",
        "发行人召开的第一届董事会第五次会议、第七次会议、第八次会议和 2022年度股东大会对发行人在 2020年度至2022 年度发生的关联交易进行了确认，对2023 年度、2024 年度的日常关联交易进行了预计，并由独立董事对该等关联交易决策程序的规范性和交易价格的公允性发表了独立意见；公司独立董事已审阅了发行人2020年度至 2022年度发生的关联交易及 2023年度、2024 年度的日常关联交易预计，该等关联交易系公司正常生产经营活动所需，交易定价合理、公允，严格遵循平等、自愿、等价、有偿的原则，符合《公司法》《公司章程》和公司关于关联交易管理的有关规定，不存在损害公司及股东特别是中小股东利益的情形，不会影响发行人的独立性，也不会对公司持续经营能力产生影响。"
      ],
      "matched_keyword": "股东"
    },
    {
      "title_hierarchy": [
        "首次公开发行股票并在创业板上市行股票并在",
        "（五）发行人拟采取的减少关联交易的措施"
      ],
      "content": [
        "对于在生产经营中因业务发展等不可避免的原因而发生的关联交易，发行人将严格按照《公司章程》《股东大会议事规则》《董事会议事规则》《独立董事工作制度》《关联交易管理制度》等对关联交易的有关条款执行，充分发挥独立董事的作用，确保关联交易决策程序的规范性和交易价格的公允性。",
        "为规范和减少与发行人之间的关联交易，发行人控股股东黄山供销集团、实际控制人黄山市供销社、全体董事、监事、高级管理人员以及其他持有发行人5%以上股份的股东出具了承诺，具体内容详见“第十二节 附件”之“四、本次发行相关主体作出的重要承诺”之“（十一）其他承诺事项”。"
      ],
      "matched_keyword": "股东"
    },
    {
      "title_hierarchy": [
        "首次公开发行股票并在创业板上市行股票并在",
        "一、本次发行前滚存利润的分配安排"
      ],
      "content": [
        "根据公司 2023 年第一次临时股东大会决议，公司本次发行前滚存的未分配利润由本次发行后的新老股东按持股比例共享。"
      ],
      "matched_keyword": "股东"
    },
    {
      "title_hierarchy": [
        "首次公开发行股票并在创业板上市行股票并在",
        "（一）本次发行后的股利分配政策"
      ],
      "content": [
        "根据公司2023 年第一次临时股东大会决议审议通过的《公司章程（草案）》，本次发行上市后公司股利分配政策主要内容如下："
      ],
      "matched_keyword": "股东"
    },
    {
      "title_hierarchy": [
        "首次公开发行股票并在创业板上市行股票并在",
        "（2）股票股利分配条件"
      ],
      "content": [
        "公司在经营情况良好，并且董事会认为公司股票价格与公司股本规模不匹配、发放股票股利有利于公司全体股东整体利益时，可以在满足上述现金分红的条件",
        "下，采用发放股票股利方式进行利润分配。股票股利分配可以单独实施，也可以结合现金分红同时实施。"
      ],
      "matched_keyword": "股东"
    },
    {
      "title_hierarchy": [
        "首次公开发行股票并在创业板上市行股票并在",
        "5、利润分配方案决策程序"
      ],
      "content": [
        "（1）公司管理层根据公司盈利情况、资金需求以及股东回报规划，合理提出利润分配建议和预案，然后由公司董事会审议制定利润分配方案。公司独立董事应发表独立意见，监事会对利润分配方案进行审议。",
        "公司董事会在制定利润分配方案时，应就利润分配方案的合理性进行充分讨论，形成专项决议，并经董事会、监事会审议通过后提交股东大会审议。",
        "（2）股东大会对利润分配方案审议前，公司应通过电话、传真、网络互动平台等多种渠道主动与股东特别是中小股东进行沟通和交流，充分听取中小股东的意见和诉求，并及时答复中小股东关心的问题。",
        "（3）股东大会在审议利润分配方案时，须经出席股东大会的股东（包括股东代理人）所持表决权的过半数通过。如股东大会审议发放股票股利或以公积金转增股本方案的，须经出席股东大会的股东（包括股东代理人）所持表决权的三分之二以上通过。公司在召开股东大会审议利润分配方案时，可以采取为股东提供网络投票表决的方式、邀请中小股东参会等多种形式，充分保障广大股东尤其是中小股东的权利。"
      ],
      "matched_keyword": "股东"
    },
    {
      "title_hierarchy": [
        "首次公开发行股票并在创业板上市行股票并在",
        "6、利润分配政策调整"
      ],
      "content": [
        "（1）公司将保持利润分配政策的连续性、稳定性，如因公司自身经营情况、投资规划和长期发展的需要，或者根据外部经营环境发生重大变化而确需调整利润分配政策的，调整后的利润分配政策不得违反中国证监会和证券交易所等的有关规定，有关调整利润分配政策议案由董事会根据公司经营状况和中国证监会的有关规定拟定，提交股东大会审议并经出席股东大会的股东所持表决权的三分之二以上通过，在股东大会提案时须进行详细论证和说明原因。",
        "（2）董事会拟定调整利润分配政策议案过程中，应当充分听取股东、独立董事和外部监事（如有）的意见。董事会审议通过调整利润分配政策议案的，应经董事会全体董事过半数以上表决通过。独立董事应当对利润分配政策的调整发表独立意见。",
        "监事会应当对董事会拟定的调整利润分配政策议案进行审议，充分听取不在公司任职的外部监事意见（如有），并经监事会全体监事过半数表决通过。"
      ],
      "matched_keyword": "股东"
    },
    {
      "title_hierarchy": [
        "首次公开发行股票并在创业板上市行股票并在",
        "7、利润分配政策的披露"
      ],
      "content": [
        "（1）公司应当在年度报告中详细披露现金分红政策的制定及执行情况，并对下列事项进行专项说明：",
        "①是否符合公司章程的规定或者股东大会决议的要求；",
        "②分红标准和比例是否明确和清晰；",
        "③相关的决策程序和机制是否完备；",
        "④独立董事是否尽职履责并发挥了应有的作用；",
        "⑤中小股东是否有充分表达意见和诉求的机会，中小股东的合法权益是否得到充分维护等。",
        "对现金分红政策进行调整或变更的，还应对调整或变更的条件和程序是否合规和透明等进行详细说明。",
        "（2）公司若当年不进行或低于本章程规定的现金分红比例进行利润分配的，董事会应当在定期报告中披露原因，独立董事应当对未分红原因、未分红的资金留存公司的用途发表独立意见，有关利润分配的议案需经公司董事会审议后提交股东大会批准，并在股东大会提案中详细论证说明原因及留存资金的具体用途。"
      ],
      "matched_keyword": "股东"
    },
    {
      "title_hierarchy": [
        "首次公开发行股票并在创业板上市行股票并在",
        "（二）董事会关于股东回报事宜的专项研究论证情况以及相应的规划安排理由等"
      ],
      "content": [
        "为进一步健全和完善公司利润分配决策和监督机制，强化公司回报股东的意识，增强公司利润分配的透明度，便于投资者形成稳定的回报预期，根据中国证券监督管理委员会发布的《关于进一步落实上市公司现金分红有关事项的通知》《上市公司监管指引第 3 号— —上市公司现金分红》等法律法规要求，公司于2023 年 2 月 2 日召开 2023 年第一次临时股东大会，审议通过了《黄山谷捷股份有限公司首次公开发行股票并在创业板上市后三年股东分红回报规划》的议案。",
        "股东分红回报规划制定的考虑因素如下：公司经营发展实际、股东要求和意愿、社会资金成本、外部融资环境等因素；公司目前及未来盈利规模、现金流量状况、发展所处阶段、资金需求等情况；公司长远可持续发展与股东合理投资回报的平衡关系。",
        "股东分红回报规划的制定原则如下：应符合相关法律法规和公司章程等的规定；应着眼于公司的长远和可持续发展；应保持利润分配政策的连续性和稳定性；应强化回报股东的意识。"
      ],
      "matched_keyword": "股东"
    },
    {
      "title_hierarchy": [
        "首次公开发行股票并在创业板上市行股票并在",
        "（三）公司上市后三年内现金分红回报规划"
      ],
      "content": [
        "2023年 2月2 日公司召开2023年第一次临时股东大会，审议通过了《黄山谷捷股份有限公司首次公开发行股票并在创业板上市后三年股东分红回报规划》，本次发行上市后未来三年股东回报规划主要内容如下："
      ],
      "matched_keyword": "股东"
    },
    {
      "title_hierarchy": [
        "首次公开发行股票并在创业板上市行股票并在",
        "1、利润分配的具体政策"
      ],
      "content": [
        "（1）公司将采取积极的利润分配政策，可以采取现金或者现金与股票相结合的方式进行利润分配。并优先采用现金分红的方式。",
        "（2）在当年盈利且未分配利润为正数的情况下，公司原则上每会计年度进行一次利润分配。公司董事会可以根据公司的盈利情况和资金需求状况，提议公司进行中期利润分配。",
        "（3）公司在当年盈利且累计未分配利润为正的情况下，采取现金方式分配股利，每年以现金方式分配的利润不少于当年实现的可分配利润的 10%。在不影响公司正常经营前提下，最近三年以现金方式累计分配的利润不少于最近三年实现的年均可分配利润的 30%。",
        "（4）存在下述情况之一时，公司当年可以不进行现金分红或现金分红比例可以低于当年实现的可分配利润的 10%：",
        "①当年实现的每股可供分配利润低于 0.1 元；",
        "②公司未来 12 个月内存在重大投资计划或重大现金支出等事项发生（募集资金项目除外）。重大投资计划或重大现金支出是指公司未来十二个月内对外投资、收购资产或购买设备累计支出超过公司最近一期经审计的合并报表净资产的10%，且绝对金额超过 3,000 万元；",
        "③当年经审计资产负债率（母公司）超过 70%；",
        "④审计机构对公司该年度财务报告出具保留意见、否定意见或无法表示意见的审计报告。",
        "（5）公司董事会应当综合考虑所处行业特点、发展阶段、自身经营模式、盈利水平以及是否有重大资金支出安排等因素，区分下列情形，提出差异化的现金分红政策：",
        "①公司发展阶段属成熟期且无重大资金支出安排的，进行利润分配时，现金分红在本次利润分配中所占比例最低应达到 80%；",
        "②公司发展阶段属成熟期且有重大资金支出安排的，进行利润分配时，现金分红在本次利润分配中所占比例最低应达到 40%；",
        "③公司发展阶段属成长期且有重大资金支出安排的，进行利润分配时，现金分红在本次利润分配中所占比例最低应达到 20%；",
        "公司发展阶段不易区分但有重大资金支出安排的，可以按照前项规定处理。",
        "（6）公司在经营情况良好，并且董事会认为公司股票价格与公司股本规模不匹配、发放股票股利有利于公司全体股东整体利益时，可以在满足上述现金分红的条件下，采用发放股票股利方式进行利润分配。股票股利分配可以单独实施，也可以结合现金分红同时实施。"
      ],
      "matched_keyword": "股东"
    },
    {
      "title_hierarchy": [
        "首次公开发行股票并在创业板上市行股票并在",
        "2、股东分红回报规划的决策机制和程序"
      ],
      "content": [
        "董事会应充分听取独立董事以及中小股东的意见，认真研究和论证公司利润分配的时机、条件和比例等，提出利润分配预案，审议通过后提交股东大会审议。"
      ],
      "matched_keyword": "股东"
    },
    {
      "title_hierarchy": [
        "首次公开发行股票并在创业板上市行股票并在",
        "3、股东分红回报规划制定周期和调整机制"
      ],
      "content": [
        "公司至少每三年重新审阅一次本规划，根据股东（特别是公众投资者）、独立董事和监事的意见对公司正在实施的利润分配政策作出适当且必要的修改，确定该时段的股东回报规划。公司保证调整后的股东回报规划不违反以下原则：在当年实现的净利润以及当年末未分配利润均为正数，且无重大资金支出安排的情况下，公司每年以现金方式累计分配的利润不少于当年度实现的可分配利润的10%，且不得违反中国证监会和证券交易所的有关规定。",
        "发行人上市后三年内的利润分配计划的制定依据参见本节之“二、股利分配政策”之“（二）董事会关于股东回报事宜的专项研究论证情况以及相应的规划安排理由等”，上述利润分配计划具有可行性。",
        "报告期内，发行人净利润分别为 3,427.86 万元、10,234.06 万元、16,346.06万元和 6,345.69 万元。截至 2024 年 6 月 30 日，发行人累计未分配利润 25,378.56万元。公司已经具备进行持续、稳定的利润分配的基础。同时，公司制定利润分配计划时还考虑了未来较长一个时期内的投资和营运资金需求，公司目前还处于增长期，考虑到未来融资环境和成本的不确定性，公司保留一定的现金储备和现金积累，为公司未来持续经营、稳定发展和满足市场需求提供必要的保证，符合公司和股东的根本利益。"
      ],
      "matched_keyword": "股东"
    },
    {
      "title_hierarchy": [
        "首次公开发行股票并在创业板上市行股票并在",
        "（一）发行人的重大诉讼或仲裁事项"
      ],
      "content": [
        "截至本招股说明书签署日，发行人及其控股子公司不存在对财务状况、经营成果、声誉、业务活动、未来前景等可能产生较大影响的重大诉讼、仲裁事项。",
        "报告期内，发行人存在一起商标诉讼案件，具体情况详见本招股说明书“第五节 业务与技术”之“五、公司经营相关的主要固定资产和无形资产等资源要素”之“（二）无形资产”之“3、商标权”。",
        "（二）控股股东或实际控制人作为一方当事人可能对发行人产生影响的刑事诉讼、重大诉讼或仲裁事项",
        "截至本招股说明书签署日，公司控股股东或实际控制人均未涉及作为一方当事人的刑事诉讼、重大诉讼或仲裁事项。",
        "（三）控股子公司作为一方当事人可能对发行人产生影响的刑事诉讼、重大诉讼或仲裁事项",
        "截至本招股说明书签署日，公司控股子公司均未涉及作为一方当事人的刑事诉讼、重大诉讼或仲裁事项。",
        "（四）发行人董事、监事、高级管理人员和其他核心人员作为一方当事人可能对发行人产生影响的刑事诉讼、重大诉讼或仲裁事项",
        "截至本招股说明书签署日，公司董事、监事、高级管理人员及其他核心人员均未涉及作为一方当事人的刑事诉讼、重大诉讼或仲裁事项。",
        "（五）董事、监事、高级管理人员和其他核心人员最近 3 年涉及行政处罚、被司法机关立案侦查、被中国证监会立案调查情况",
        "报告期内，公司的董事、监事、高级管理人员和核心技术人员不存在涉及行政处罚、被司法机关立案侦查、被中国证监会立案调查情况。"
      ],
      "matched_keyword": "股东"
    },
    {
      "title_hierarchy": [
        "首次公开发行股票并在创业板上市行股票并在",
        "发行人控股股东声明"
      ],
      "content": [
        "本公司承诺本招股说明书的内容真实、准确、完整，不存在虚假记载、误导性陈述或重遗漏，按照诚信原则履承诺，并承担相应的法律责任。",
        "法定代表人：",
        "家成",
        "冯家成",
        "![](images/7b80428a162af0d7ebc9aa5a6d27a9340e90439bf76a5011961857fe77139f84.jpg)",
        "<details>",
        "<summary>seal</summary>",
        "萧山耕销集团有限公司",
        "14100201122",
        "</details>"
      ],
      "matched_keyword": "股东"
    },
    {
      "title_hierarchy": [
        "首次公开发行股票并在创业板上市行股票并在",
        "一、附件目录"
      ],
      "content": [
        "（一）发行保荐书；",
        "（二）上市保荐书；",
        "（三）法律意见书；",
        "（四）财务报表及审计报告；",
        "（五）公司章程（草案）；",
        "（六）落实投资者关系管理相关规定的安排、股利分配决策程序、股东投票机制建立情况；",
        "（七）与投资者保护相关的承诺；",
        "（八）发行人及其他责任主体作出的与发行人本次发行上市相关的其他承诺事项；",
        "（九）发行人审计报告基准日至招股说明书签署日之间的相关财务报告及审阅报告；",
        "（十）内部控制鉴证报告；",
        "（十一）经注册会计师鉴证的非经常性损益明细表；",
        "（十二）股东大会、董事会、监事会、独立董事、董事会秘书制度的建立健全及运行情况说明；",
        "（十三）审计委员会及其他专门委员会的设置情况说明；",
        "（十四）募集资金具体运用情况；",
        "（十五）子公司、参股公司简要情况；",
        "（十六）其他与本次发行有关的重要文件。"
      ],
      "matched_keyword": "股东"
    },
    {
      "title_hierarchy": [
        "首次公开发行股票并在创业板上市行股票并在",
        "3、未来开展投资者关系管理的规划"
      ],
      "content": [
        "公司将严格按照《公司法》《证券法》《深圳证券交易所创业板股票上市规则》等相关法律法规和《公司章程（草案）》《投资者关系管理制度》的要求，认真履行信息披露义务，切实开展投资者关系构建、管理和维护，为投资者和公司搭建起畅通的沟通交流平台。",
        "公司将不断提高公司投资者关系管理工作的专业性，加强投资者对公司的了解，促进公司与投资者之间的良性互动关系，切实维护全体股东利益，特别是中小股东的利益，努力实现公司价值最大化和股东利益最大化。"
      ],
      "matched_keyword": "股东"
    },
    {
      "title_hierarchy": [
        "首次公开发行股票并在创业板上市行股票并在",
        "（二）股利分配决策程序"
      ],
      "content": [
        "1、公司管理层根据公司盈利情况、资金需求以及股东回报规划，合理提出利润分配建议和预案，然后由公司董事会审议制定利润分配方案。公司独立董事应发表独立意见，监事会对利润分配方案进行审议。",
        "公司董事会在制定利润分配方案时，应就利润分配方案的合理性进行充分讨论，形成专项决议，并经董事会、监事会审议通过后提交股东大会审议。",
        "2、股东大会对利润分配方案审议前，公司应通过电话、传真、网络等多种渠道主动与股东特别是中小股东进行沟通和交流，充分听取中小股东的意见和诉求，并及时答复中小股东关心的问题。",
        "3、股东大会在审议利润分配方案时，须经出席股东大会的股东（包括股东代理人）所持表决权的过半数通过。如股东大会审议发放股票股利或以公积金转增股本方案的，须经出席股东大会的股东（包括股东代理人）所持表决权的三分",
        "之二以上通过。公司在召开股东大会审议利润分配方案时，可以采取为股东提供网络投票表决的方式、邀请中小股东参会等多种形式，充分保障广大股东尤其是中小股东的权利。"
      ],
      "matched_keyword": "股东"
    },
    {
      "title_hierarchy": [
        "首次公开发行股票并在创业板上市行股票并在",
        "1、中小投资者单独计票机制"
      ],
      "content": [
        "根据《公司章程（草案）》及《股东大会议事规则》的规定，股东大会审议影响中小投资者利益的重大事项时，对中小投资者表决应当单独计票。"
      ],
      "matched_keyword": "股东"
    },
    {
      "title_hierarchy": [
        "首次公开发行股票并在创业板上市行股票并在",
        "2、征集投票权"
      ],
      "content": [
        "根据《公司章程（草案）》及《股东大会议事规则》的规定，公司董事会、独立董事、持有百分之一以上有表决权股份的股东或者依照法律、行政法规或者中国证监会的规定设立的投资者保护机构可以公开征集股东投票权。征集股东投票权应当向被征集人充分披露具体投票意向等信息。禁止以有偿或者变相有偿的方式征集股东投票权。公司不得对征集投票权提出最低持股比例限制。"
      ],
      "matched_keyword": "股东"
    },
    {
      "title_hierarchy": [
        "首次公开发行股票并在创业板上市行股票并在",
        "3、网络投票制"
      ],
      "content": [
        "根据《公司章程（草案）》及《股东大会议事规则》相关规定，股东大会应当设置会场，以现场会议形式召开，并应当按照法律、行政法规、中国证监会或公司章程的规定，采用安全、经济、便捷的网络和其他方式为股东参加股东大会提供便利。股东通过上述方式参加股东大会的，视为出席。"
      ],
      "matched_keyword": "股东"
    },
    {
      "title_hierarchy": [
        "首次公开发行股票并在创业板上市行股票并在",
        "4、累积投票制"
      ],
      "content": [
        "根据《公司章程（草案）》及《股东大会议事规则》相关规定，股东大会就选举董事、非由职工代表担任的监事进行表决时，可以实行累积投票制。前款所称累积投票制是指股东大会选举董事或者监事时，每一股份拥有与应选董事或者监事人数相同的表决权，股东拥有的表决权可以集中使用。"
      ],
      "matched_keyword": "股东"
    },
    {
      "title_hierarchy": [
        "首次公开发行股票并在创业板上市行股票并在",
        "1、控股股东黄山供销集团、实际控制人黄山市供销社承诺"
      ],
      "content": [
        "（1）自发行人股票上市之日起 36个月内，不转让或者委托他人管理本承诺人于本次公开发行前已持有的发行人股份，也不由发行人回购该部分股份。",
        "（2）本承诺人若在锁定期满后两年内减持发行人股票的，减持价格不低于本次发行价；发行人上市后 6 个月内如发行人股票连续 20 个交易日的收盘价均低于本次发行价，或者上市后 6个月期末收盘价低于本次发行价，本承诺人持有的发行人股票锁定期将自动延长 6 个月。在延长锁定期内，本承诺人不转让或者委托他人管理本承诺人在公司本次发行前持有的公司股份，也不由公司回购该部分股份。",
        "（3）自发行人股票上市至减持期间，如有派发现金股利、送股、转增股本、增发新股等除权除息事项，上述减持价格及收盘价等将按照中国证监会、深圳证券交易所相关规定做相应调整。",
        "（4）法律、行政法规、中国证监会行政规章、证券交易所业务规则及其他规范性文件对本承诺人转让发行人股份存在其他限制的，本承诺人承诺同意一并遵守。在本承诺人持股期间，若股份锁定和减持的法律、法规、规范性文件、政策及证券监管机构的要求发生变化，则本承诺人愿意自动适用变更后的法律、法规、规章、规范性文件、政策及证券监管机构的要求。",
        "如本承诺人违反上述承诺，本承诺人因违反上述承诺而产生的任何收益归发行人所有，并赔偿因未履行上述承诺而给发行人或投资者带来的损失。"
      ],
      "matched_keyword": "股东"
    },
    {
      "title_hierarchy": [
        "首次公开发行股票并在创业板上市行股票并在",
        "2、担任公司董事、高级管理人员的股东张俊武、周斌、罗仁棠、程家斌、汪琦承诺"
      ],
      "content": [
        "（1）自发行人股票上市之日起 12个月内，不转让或者委托他人管理本承诺人于本次公开发行前已持有的发行人股份，也不由发行人回购该部分股份。",
        "（2）本承诺人若在锁定期满后两年内减持发行人股票的，减持价格不低于本次发行价；发行人上市后 6 个月内如发行人股票连续 20 个交易日的收盘价均低于本次发行价，或者上市后 6个月期末收盘价低于本次发行价，本承诺人持有的发行人股票锁定期将自动延长 6个月。在延长锁定期内，本承诺人不转让或者委托他人管理本承诺人在本次公开发行前持有的公司股份，也不由公司回购该部分股份。",
        "（3）自发行人股票上市至减持期间，如有派发现金股利、送股、转增股本、增发新股等除权除息事项，上述减持价格及收盘价等将按照中国证监会、深圳证券交易所相关规定做相应调整。",
        "（4）锁定期届满后，本承诺人在发行人担任董事/高级管理人员期间每年转让的股份不超过本承诺人所持有发行人股份总数的 25%；离职后半年内，不转让本承诺人所持有的发行人股份。如本承诺人在任期届满前离职的，本承诺人承诺在本承诺人就任时确定的任期内和任期届满后 6 个月内，继续遵守上述对董事/高级管理人员股份转让的限制性规定。",
        "（5）法律、行政法规、中国证监会行政规章、证券交易所业务规则及其他规范性文件对本承诺人转让公司股份存在其他限制的，本承诺人承诺一并遵守。在本承诺人持股期间，若股份锁定和减持的法律、法规、规范性文件、政策及证券监管机构的要求发生变化，则本承诺人愿意自动适用变更后的法律、法规、规章、规范性文件、政策及证券监管机构的要求。",
        "（6）在上述承诺履行期间，本承诺人职务变更、离职等原因不影响本承诺的效力，在此期间本承诺人仍将继续履行上述承诺。",
        "如本承诺人违反上述承诺，本承诺人因违反上述承诺而产生的任何收益归发行人所有，并赔偿因未履行上述承诺而给发行人或投资者带来的损失。"
      ],
      "matched_keyword": "股东"
    },
    {
      "title_hierarchy": [
        "首次公开发行股票并在创业板上市行股票并在",
        "3、担任公司监事的股东谷伟承诺"
      ],
      "content": [
        "（1）自发行人股票上市之日起 12个月内，不转让或者委托他人管理本承诺人于本次公开发行前已持有的发行人股份，也不由发行人回购该部分股份。",
        "（2）锁定期届满后，本承诺人在发行人担任监事期间每年转让的股份不超过本承诺人所持有发行人股份总数的25%；离职后半年内，不转让本承诺人所持有的发行人股份。如本承诺人在任期届满前离职的，本承诺人承诺在本承诺人就任时确定的任期内和任期届满后 6 个月内，继续遵守上述对监事股份转让的限制",
        "性规定。",
        "（3）法律、行政法规、中国证监会行政规章、证券交易所业务规则及其他规范性文件对本承诺人转让公司股份存在其他限制的，本承诺人承诺一并遵守。在本承诺人持股期间，若股份锁定和减持的法律、法规、规范性文件、政策及证券监管机构的要求发生变化，则本承诺人愿意自动适用变更后的法律、法规、规章、规范性文件、政策及证券监管机构的要求。",
        "（4）在上述承诺履行期间，本承诺人职务变更、离职等原因不影响本承诺的效力，在此期间本承诺人仍将继续履行上述承诺。",
        "如本承诺人违反上述承诺，本承诺人因违反上述承诺而产生的任何收益归发行人所有，并赔偿因未履行上述承诺而给发行人或投资者带来的损失。"
      ],
      "matched_keyword": "股东"
    },
    {
      "title_hierarchy": [
        "首次公开发行股票并在创业板上市行股票并在",
        "4、持股 5%以上的股东赛格高技术、黄山佳捷承诺"
      ],
      "content": [
        "持股5%以上的股东赛格高技术承诺：",
        "（1）自发行人股票上市之日起12个月内，不转让或者委托他人管理本承诺人于本次公开发行前已持有的发行人股份，也不由发行人回购该部分股份。",
        "（2）法律、行政法规、中国证监会行政规章、证券交易所业务规则及其他规范性文件对本承诺人转让公司股份存在其他限制的，本承诺人承诺一并遵守。在本承诺人持股期间，若股份锁定和减持的法律、法规、规范性文件、政策及证券监管机构的要求发生变化，则本承诺人愿意自动适用变更后的法律、法规、规章、规范性文件、政策及证券监管机构的要求。",
        "如本承诺人违反上述承诺，本承诺人因违反上述承诺而产生的任何收益归发行人所有，并赔偿因未履行上述承诺而给发行人或投资者带来的损失。",
        "持股5%以上的股东黄山佳捷作为发行人申报前一年内新增股东，承诺：",
        "（1）自发行人股票上市之日起 12个月内或自本合伙企业取得发行人股份之日起 36 个月内（以孰晚为准），不转让或者委托他人管理本承诺人于本次公开发行前已持有的发行人股份，也不由发行人回购该部分股份。",
        "（2）法律、行政法规、中国证监会行政规章、证券交易所业务规则及其他规范性文件对本承诺人转让发行人股份存在其他限制的，本承诺人承诺一并遵守。",
        "在本承诺人持股期间，若股份锁定和减持的法律、法规、规范性文件、政策及证券监管机构的要求发生变化，则本承诺人愿意自动适用变更后的法律、法规、规章、规范性文件、政策及证券监管机构的要求。",
        "如本承诺人违反上述承诺，本承诺人因违反上述承诺而产生的任何收益归发行人所有，并赔偿因未履行上述承诺而给发行人或投资者带来的损失。"
      ],
      "matched_keyword": "股东"
    },
    {
      "title_hierarchy": [
        "首次公开发行股票并在创业板上市行股票并在",
        "5、股东上汽科技承诺"
      ],
      "content": [
        "（1）自发行人股票上市之日起12个月内，不转让或者委托他人管理本承诺人于本次公开发行前已持有的发行人股份，也不由发行人回购该部分股份。",
        "（2）法律、行政法规、中国证监会行政规章、证券交易所业务规则及其他规范性文件对本承诺人转让发行人股份存在其他限制的，本承诺人承诺一并遵守。在本承诺人持股期间，若股份锁定和减持的法律、法规、规范性文件、政策及证券监管机构的要求发生变化，则本承诺人愿意自动适用变更后的法律、法规、规章、规范性文件、政策及证券监管机构的要求。",
        "如本承诺人违反上述承诺，本承诺人因违反上述承诺而产生的任何收益归发行人所有，并赔偿因未履行上述承诺而给发行人或投资者带来的损失。"
      ],
      "matched_keyword": "股东"
    },
    {
      "title_hierarchy": [
        "首次公开发行股票并在创业板上市行股票并在",
        "1、控股股东黄山供销集团、实际控制人黄山市供销社承诺"
      ],
      "content": [
        "（1）本承诺人持续看好公司的发展前景，愿意长期持有公司股票；本承诺人承诺严格根据中国证监会、深圳证券交易所等有权部门颁布的相关法律、法规及规范性文件的有关规定，履行相关股份锁定承诺事项，在中国证监会、深圳证券交易所等有权部门颁布的相关法律、法规及规范性文件的有关规定以及股份锁定承诺规定的限售期内，承诺不进行任何违反相关规定及股份锁定承诺的股份减持行为。",
        "（2）股份锁定期届满后，本承诺人拟减持本次公开发行前股份的，将认真遵守中国证监会、深圳证券交易所关于股东减持的相关规定，审慎制定股票减持计划，明确并披露发行人的控制权安排，保证公司持续稳定经营。本承诺人在锁定期满后两年内减持公司股份的，减持价格不低于发行价（如公司上市后有派息、送股、资本公积转增股本、配股及增发等除权除息事项，发行价将相应进行调整），减持比例不超过有关法律法规或中国证监会和深圳证券交易所对本承诺人持有的本次公开发行前股份的限售规定。",
        "（3）本承诺人通过集中竞价交易方式减持公司股票，将在首次减持前 15个交易日予以公告，通过其他方式减持公司股票，将在减持前 3个交易日予以公告，并按照证券监管机构、证券交易所届时适用的规则及时、准确地履行信息披露义务。",
        "（4）本承诺人减持公司股份应符合相关法律、法规、规章的规定，具体方式包括但不限于交易所集中竞价交易方式、大宗交易方式、协议转让方式等。",
        "如本承诺人违反上述承诺，本承诺人因违反上述承诺而产生的任何收益归发行人所有，并赔偿因未履行上述承诺而给发行人或投资者带来的损失。"
      ],
      "matched_keyword": "股东"
    },
    {
      "title_hierarchy": [
        "首次公开发行股票并在创业板上市行股票并在",
        "2、担任公司董事、高级管理人员的股东张俊武、周斌、罗仁棠、程家斌、汪琦承诺"
      ],
      "content": [
        "（1）本承诺人持续看好公司的发展前景，愿意长期持有公司股票；本承诺人承诺严格根据中国证监会、深圳证券交易所等有权部门颁布的相关法律、法规及规范性文件的有关规定，履行相关股份锁定承诺事项，在中国证监会、深圳证券交易所等有权部门颁布的相关法律、法规及规范性文件的有关规定以及股份锁定承诺规定的限售期内，承诺不进行任何违反相关规定及股份锁定承诺的股份减持行为。",
        "（2）股份锁定期届满后，本承诺人拟减持本次公开发行前股份的，将认真遵守中国证监会、深圳证券交易所关于股东减持的相关规定，审慎制定股票减持计划，保证公司持续稳定经营。本承诺人在锁定期满后两年内减持公司股份的，减持价格不低于发行价（如公司上市后有派息、送股、资本公积转增股本、配股及增发等除权除息事项，发行价将相应进行调整），减持比例不超过有关法律法规或中国证监会和深圳证券交易所对本承诺人持有的本次公开发行前股份的限售规定。",
        "（3）本承诺人承诺减持公司股份时，将按照届时有效的规则提前将减持计划以书面方式通知公司，并按照深圳证券交易所的规则及时、准确地履行信息披",
        "露义务。",
        "（4）本承诺人减持公司股份应符合相关法律、法规、规章的规定，具体方式包括但不限于交易所集中竞价交易方式、大宗交易方式、协议转让方式等。",
        "如本承诺人违反上述承诺，本承诺人因违反上述承诺而产生的任何收益归发行人所有，并赔偿因未履行上述承诺而给发行人或投资者带来的损失。"
      ],
      "matched_keyword": "股东"
    },
    {
      "title_hierarchy": [
        "首次公开发行股票并在创业板上市行股票并在",
        "3、担任公司监事的股东谷伟承诺"
      ],
      "content": [
        "（1）本承诺人持续看好公司的发展前景，愿意长期持有公司股票；本承诺人承诺严格根据中国证监会、深圳证券交易所等有权部门颁布的相关法律、法规及规范性文件的有关规定，履行相关股份锁定承诺事项，在中国证监会、深圳证券交易所等有权部门颁布的相关法律、法规及规范性文件的有关规定以及股份锁定承诺规定的限售期内，承诺不进行任何违反相关规定及股份锁定承诺的股份减持行为。",
        "（2）股份锁定期届满后，本承诺人拟减持本次公开发行前股份的，将认真遵守中国证监会、深圳证券交易所关于股东减持的相关规定，审慎制定股票减持计划，保证公司持续稳定经营。",
        "（3）本承诺人减持公司股份时，将按照届时有效的规则提前将减持计划以书面方式通知公司，并按照深圳证券交易所的规则及时、准确地履行信息披露义务。",
        "（4）本承诺人减持公司股份应符合相关法律、法规、规章的规定，具体方式包括但不限于交易所集中竞价交易方式、大宗交易方式、协议转让方式等。",
        "如本承诺人违反上述承诺，本承诺人因违反上述承诺而产生的任何收益归发行人所有，并赔偿因未履行上述承诺而给发行人或投资者带来的损失。"
      ],
      "matched_keyword": "股东"
    },
    {
      "title_hierarchy": [
        "首次公开发行股票并在创业板上市行股票并在",
        "4、持股 5%以上的股东赛格高技术、黄山佳捷、张俊武、周斌承诺"
      ],
      "content": [
        "（1）本承诺人持续看好公司的发展前景，愿意长期持有公司股票；本承诺人承诺严格根据中国证监会、深圳证券交易所等有权部门颁布的相关法律、法规及规范性文件的有关规定，履行相关股份锁定承诺事项，在中国证监会、深圳证券交易所等有权部门颁布的相关法律、法规及规范性文件的有关规定以及股份锁定承诺规定的限售期内，承诺不进行任何违反相关规定及股份锁定承诺的股份减持行为。",
        "（2）股份锁定期届满后，本承诺人拟减持本次公开发行前股份的，将认真遵守中国证监会、证券交易所关于股东减持的相关规定，审慎制定股票减持计划，明确并披露发行人的控制权安排，保证公司持续稳定经营。本承诺人在锁定期满后两年内减持公司股份的，减持价格不低于发行价（如公司上市后有派息、送股、资本公积转增股本、配股及增发等除权除息事项，发行价将相应进行调整），减持比例不超过有关法律法规或中国证监会和证券交易所对本承诺人持有的本次公开发行前股份的限售规定。",
        "（3）本承诺人通过集中竞价交易方式减持公司股票，将在首次减持前 15个交易日予以公告，通过其他方式减持公司股票，将在减持前 3个交易日予以公告，并按照证券监管机构、证券交易所届时适用的规则及时、准确地履行信息披露义务。",
        "（4）本承诺人减持公司股份应符合相关法律、法规、规章的规定，具体方式包括但不限于交易所集中竞价交易方式、大宗交易方式、协议转让方式等。",
        "如本承诺人违反上述承诺，本承诺人因违反上述承诺而产生的任何收益归发行人所有，并赔偿因未履行上述承诺而给发行人或投资者带来的损失。"
      ],
      "matched_keyword": "股东"
    },
    {
      "title_hierarchy": [
        "首次公开发行股票并在创业板上市行股票并在",
        "（1）公司回购股份"
      ],
      "content": [
        "当达到启动条件时，公司将根据《上市公司股份回购规则》等相关法律法规的规定向社会公众股东回购公司部分股票，以稳定公司股价。",
        "①启动稳定股价预案的程序",
        "a.公司董事会办公室负责前述触发实施稳定股价方案条件的监测，在其监测到前述触发实施稳定股价方案条件成就时，公司于 10 日内召开董事会讨论稳定股价方案，并经公司全体董事三分之二以上表决通过；如根据法律及中国证监会、深圳证券交易所等相关规定，需提交股东大会审议的，公司董事会应于董事会表决通过之日起2个交易日内发出召开股东大会的通知，并于发出股东大会会议通知后的 15 个交易日内召开股东大会审议；公司股东大会对回购股份做出决议，须经出席会议的股东所持表决权的三分之二以上通过；",
        "b.公司应在股东大会决议做出之日起次日开始启动回购程序，并应在履行相关法定手续后的30 个交易日内实施完毕；",
        "c.公司回购方案实施完毕后，应在 2个交易日内公告公司股份变动报告，并按照中国证监会或深圳证券交易所规定的方式对回购股份进行处置。",
        "②公司回购股份的资金为自有资金，回购股份的方式为集中竞价交易方式、要约方式或证券监督管理部门认可的其他方式。但如果股份回购方案实施前或实施过程中，公司股票价格连续 5个交易日的收盘价均高于每股净资产，则公司可不再继续实施该方案。",
        "③公司为稳定股价之目的进行股份回购的，除应符合相关法律法规之要求之外，还应符合下列各项条件：",
        "a.公司单一会计年度用于回购股份的资金总额累计不超过上一会计年度经审计的归属于母公司股东的可分配利润的 50%，且单次用于回购股份的资金总额不低于200万元；",
        "b.公司单次回购股份不超过当次股份回购方案实施前公司总股本的 2%；",
        "c.公司回购股份不违反公司签署的相关协议的约定，且不会导致公司的股权分布不符合上市条件。",
        "④在公司实施股份回购时，如上述相关措施与届时法律法规或监管部门相关政策相冲突，公司将按照最新的监管政策进行调整。"
      ],
      "matched_keyword": "股东"
    },
    {
      "title_hierarchy": [
        "首次公开发行股票并在创业板上市行股票并在",
        "（2）控股股东增持公司股份"
      ],
      "content": [
        "若前述股价稳定措施已实施，再次触发股价稳定措施启动条件的，且公司回购股份达到预案上限的，公司控股股东将按照有关法律法规的规定，增持公司股份。控股股东及其控制的关联股东将在公司审议股份回购方案进行投票时以所拥有的全部表决票数在股东大会上投赞成票。"
      ],
      "matched_keyword": "股东"
    },
    {
      "title_hierarchy": [
        "首次公开发行股票并在创业板上市行股票并在",
        "①启动稳定股价预案的程序"
      ],
      "content": [
        "a.公司控股股东将于触发实施稳定股价方案的 10 个交易日内通知公司董事会增持公司股份的计划，并通过公司发布增持公告；",
        "b.公司控股股东将在增持公告发布之日起次日开始启动增持，并应在履行相关法定手续后的30 个交易日内实施完毕。",
        "②增持股份的方式为集中竞价交易方式、要约方式或证券监督管理部门认可的其他方式。在增持股份不会导致公司的股权分布不符合上市条件的前提下，单次用于增持的资金总额不低于 200 万元，单次增持股份不超过当次股份增持方案实施前公司总股本的 2%。但如果股份增持方案实施前或实施过程中，公司股票价格连续5个交易日的收盘价均高于公司每股净资产，则公司控股股东可不再继续实施该方案。",
        "③在公司控股股东实施股份回购时，如上述相关措施与届时法律法规或监管部门相关政策相冲突，公司控股股东将按照最新的监管政策进行调整。"
      ],
      "matched_keyword": "股东"
    },
    {
      "title_hierarchy": [
        "首次公开发行股票并在创业板上市行股票并在",
        "（3）非独立董事、高级管理人员增持公司股份"
      ],
      "content": [
        "若前述股价稳定措施已实施，再次触发股价稳定措施启动条件的，且公司控股股东增持股份达到预案上限的，公司董事（不包括独立董事，下同）、高级管理人员将按照有关法律法规的规定，增持公司股份。"
      ],
      "matched_keyword": "股东"
    },
    {
      "title_hierarchy": [
        "首次公开发行股票并在创业板上市行股票并在",
        "3、未能履行稳定股价方案的约束措施"
      ],
      "content": [
        "（1）若公司未能履行、确已无法履行或无法按期履行前述稳定股价措施的（因相关法律法规、政策变化、自然灾害及其他不可抗力等无法控制的客观原因导致的除外），将采取以下措施：",
        "①及时、充分披露公司未能履行、无法履行或无法按期履行的具体原因；",
        "②向投资者赔偿相应损失，并进一步提出补充承诺或替代承诺，以尽可能保护投资者的权益；",
        "③将上述补充承诺或替代承诺提交公司股东大会审议。",
        "（2）若公司控股股东、董事（不含独立董事）、高级管理人员未能履行、确已无法履行或无法按期履行前述稳定股价措施的（因相关法律法规、政策变化、自然灾害及其他不可抗力等无法控制的客观原因导致的除外），公司应暂时扣留其现金分红和工资、薪酬及津贴，直至其履行上述相关义务之日止。",
        "公司若有新聘任董事（不含独立董事）、高级管理人员，公司将要求其接受未履行稳定股价方案的约束措施。"
      ],
      "matched_keyword": "股东"
    },
    {
      "title_hierarchy": [
        "首次公开发行股票并在创业板上市行股票并在",
        "（1）发行人承诺"
      ],
      "content": [
        "①本公司将严格按照《稳定股价预案》之规定全面且有效地履行本公司在《稳定股价预案》项下的各项义务和责任。",
        "②公司将极力敦促本公司控股股东及相关方严格按照《稳定股价预案》之规定全面且有效地履行其在《稳定股价预案》项下的各项义务和责任。",
        "③若本公司新聘任董事（不包括独立董事）、高级管理人员，本公司将要求新聘任的董事、高级管理人员履行本公司上市时董事、高级管理人员就《稳定股价预案》作出的相应承诺。",
        "④若非因相关法律法规、政策变化、自然灾害及其他不可抗力等原因，本公司未遵守上述承诺的，本公司将在股东大会及中国证监会指定报刊上公开说明未履行的具体原因并向股东和社会公众投资者道歉，同时按中国证监会及其他有关机关认定的实际损失向投资者进行赔偿，以尽可能保护投资者的权益。"
      ],
      "matched_keyword": "股东"
    },
    {
      "title_hierarchy": [
        "首次公开发行股票并在创业板上市行股票并在",
        "（2）控股股东黄山供销集团承诺"
      ],
      "content": [
        "①本公司将严格按照《稳定股价预案》之规定全面且有效地履行本公司在《稳定股价预案》项下的各项义务和责任。",
        "②本公司将极力敦促公司及相关方严格按照《稳定股价预案》之规定全面且有效地履行其在《稳定股价预案》项下的各项义务和责任。",
        "③如未履行上述承诺，本公司将在发行人股东大会及中国证监会指定报刊上公开说明未履行的具体原因并向发行人股东和社会公众投资者道歉；并在前述事",
        "项发生之日起停止在公司处领取股东分红，同时本公司持有的发行人股份将不得转让，直至采取相应的稳定股价措施并实施完毕时为止。"
      ],
      "matched_keyword": "股东"
    },
    {
      "title_hierarchy": [
        "首次公开发行股票并在创业板上市行股票并在",
        "（3）非独立董事、高级管理人员承诺"
      ],
      "content": [
        "①本人将严格按照《稳定股价预案》之规定全面且有效地履行本人在《稳定股价预案》项下的各项义务和责任。",
        "②本人将极力敦促公司及相关方严格按照《稳定股价预案》之规定全面且有效地履行其在《稳定股价预案》项下的各项义务和责任。",
        "③如未履行上述承诺，本人将在发行人股东大会及中国证监会指定报刊上公开说明未履行的具体原因并向公司股东和社会公众投资者道歉；并在前述事项发生之日起停止在公司处领取薪酬（如有）及股东分红（如有），同时本人持有的公司股份（如有）将不得转让，直至采取相应的稳定股价措施并实施完毕时为止。"
      ],
      "matched_keyword": "股东"
    },
    {
      "title_hierarchy": [
        "首次公开发行股票并在创业板上市行股票并在",
        "2、控股股东黄山供销集团承诺"
      ],
      "content": [
        "如证券监督管理部门或其他有权部门认定《招股说明书》所载之内容存在任何虚假记载、误导性陈述或者重大遗漏之情形，且该等情形对判断发行人是否符合法律规定的发行条件构成重大且实质影响的，则本单位承诺将按照《黄山谷捷股份有限公司之控股股东关于依法承担赔偿责任的承诺》极力促使发行人依法回购或由本单位依法回购其本次公开发行的全部新股。",
        "如中国证监会认定发行人不符合发行上市条件，以欺骗手段骗取发行注册，则本单位承诺将按照《黄山谷捷股份有限公司之控股股东关于欺诈发行上市的股份购回承诺》依法从投资者手中购回本次公开发行的全部新股。",
        "当《黄山谷捷股份有限公司首次公开发行人民币普通股（A股）股票并在创业板上市后三年内稳定股价预案》中约定的预案触发条件成就时，本单位将按照《黄山谷捷股份有限公司之控股股东关于稳定上市后公司股价的承诺》履行回购公司股份的义务。",
        "以上为本单位关于股份回购和股份购回的措施和承诺，如本单位未能依照上述承诺履行义务的，本单位将依照未能履行承诺时的约束措施承担相应责任。"
      ],
      "matched_keyword": "股东"
    },
    {
      "title_hierarchy": [
        "首次公开发行股票并在创业板上市行股票并在",
        "（五）填补被摊薄即期回报的措施和承诺"
      ],
      "content": [
        "为填补公司首次公开发行股票摊薄即期回报的影响，增强公司持续回报能力，充分保护中小股东的利益，公司制定了《关于公司首次公开发行股票摊薄即期回报及填补措施和相关主体承诺的方案》，具体内容如下：",
        "1、为维护中小投资者利益，公司将采取以下措施降低即期回报被摊薄的风险，但本公司制定的填补回报措施不等于对发行人未来利润做出保证："
      ],
      "matched_keyword": "股东"
    },
    {
      "title_hierarchy": [
        "首次公开发行股票并在创业板上市行股票并在",
        "（2）积极实施募投项目，提升市场竞争力"
      ],
      "content": [
        "为扩大公司主营业务规模及提高市场占有率，通过充分的可行性分析，确认公司的募集资金投资项目。在募集资金到位前，为尽快实现募投项目效益，公司拟通过多种渠道积极筹措资金，努力调配各方面资源，开展募投项目的前期准备工作。募集资金到位后，通过组织募集资金投资项目的实施，实现项目效益，增强股东回报。"
      ],
      "matched_keyword": "股东"
    },
    {
      "title_hierarchy": [
        "首次公开发行股票并在创业板上市行股票并在",
        "（3）优化投资回报机制"
      ],
      "content": [
        "公司在《公司章程（草案）》中已按照《上市公司监管指引第 3 号——上市公司现金分红（2023 年修订）》《上市公司章程指引（2023 年修订）》的相关规定，结合公司实际情况，制定公司上市后利润分配方案。公司首次公开发行股票并在创业板上市后，公司将严格按照《公司章程（草案）》的相关规定，建立健全有效的股东回报机制，重视对投资者的合理回报，保持利润分配政策的稳定性和连续性。",
        "如未履行上述承诺，公司将在股东大会及中国证监会指定报刊上公开说明未履行的具体原因并向股东和社会公众投资者道歉。"
      ],
      "matched_keyword": "股东"
    },
    {
      "title_hierarchy": [
        "首次公开发行股票并在创业板上市行股票并在",
        "（1）控股股东黄山供销集团、实际控制人黄山市供销社承诺："
      ],
      "content": [
        "①不越权干预发行人经营管理活动，不侵占发行人利益。",
        "②督促发行人切实履行填补回报措施。",
        "③本承诺出具日后至发行人本次发行完毕前，若中国证监会和深圳证券交易所作出关于填补回报措施及其承诺的其他新的监管规定的，且上述承诺不能满足中国证监会和深圳证券交易所该等规定时，本单位承诺届时将按照中国证监会和深圳证券交易所的最新规定出具补充承诺。",
        "如未履行上述承诺，本单位将在发行人股东大会及中国证监会指定报刊上公开说明未履行的具体原因并向发行人股东和社会公众投资者道歉；若因本单位违反该等承诺给发行人或者投资者造成损失的，本单位愿意依法承担对发行人或者投资者的补偿责任。"
      ],
      "matched_keyword": "股东"
    },
    {
      "title_hierarchy": [
        "首次公开发行股票并在创业板上市行股票并在",
        "（2）董事、高级管理人员承诺："
      ],
      "content": [
        "①承诺不得无偿或以不公平条件向其他单位或者个人输送利益，也不得采用其他方式损害公司利益。",
        "②承诺将全力支持和配合公司规范董事和高级管理人员的职务消费行为，包括但不限于参与讨论或拟定关于约束董事和高级管理人员职务消费行为的制度和规定。同时，本人将严格按照相关上市公司规定及公司内部相关管理制度的规定或要求约束本人的职务消费行为。",
        "③承诺不得动用公司资产从事与本人履行职责无关的投资、消费活动。",
        "④承诺积极推动公司薪酬制度的完善，使之更符合摊薄即期填补回报的要求；支持公司董事会或薪酬与考核委员会在制订、修改补充公司的薪酬制度时与公司填补回报措施的执行情况相挂钩。",
        "⑤承诺在推动公司股权激励（如有）时，应使股权激励行权条件与公司填补回报措施的执行情况相挂钩。",
        "如未履行上述承诺，本人将在公司股东大会及中国证监会指定报刊上公开说明未履行的具体原因并向公司股东和社会公众投资者道歉；若因本人违反该等承诺给公司或者投资者造成损失的，本人愿意依法承担对公司或者投资者的补偿责任。"
      ],
      "matched_keyword": "股东"
    },
    {
      "title_hierarchy": [
        "首次公开发行股票并在创业板上市行股票并在",
        "（六）发行人关于利润分配政策的承诺"
      ],
      "content": [
        "黄山谷捷股份有限公司（以下简称“本公司”、“公司”）拟首次公开发行股票并在创业板上市，本公司将严格遵守上市后适用的《黄山谷捷股份有限公司章程（草案）》、股东大会审议通过的上市后三年分红回报规划以及本公司股东大会审议通过的其他利润分配政策的安排，实施积极的利润分配政策及分红回报规划，注重对股东的合理回报并兼顾公司的可持续发展，保持公司利润分配政策的连续性和稳定性。",
        "公司如违反前述承诺，将在公司股东大会及中国证监会指定报刊上公开说明具体原因，并向公司股东和社会公众投资者道歉（因不可抗力或其他非归属于公司的原因除外），同时公司将及时改正并继续履行上述承诺或及时作出合法、合理、有效的补充承诺或替代承诺，以尽可能保护投资者的利益。"
      ],
      "matched_keyword": "股东"
    },
    {
      "title_hierarchy": [
        "首次公开发行股票并在创业板上市行股票并在",
        "1、发行人承诺"
      ],
      "content": [
        "本公司保证本次公开发行股票并在创业板上市不存在任何欺诈发行的情形；若本公司不符合发行上市条件，以欺骗手段骗取发行注册并已经发行上市的，本公司承诺将在中国证监会等有权部门确认后 5个工作日内启动股份回购程序，从投资者手中购回本次公开发行的全部股票。",
        "若公司违反上述承诺，公司将在股东大会及中国证监会指定报刊上公开说明具体原因及向股东和社会公众投资者道歉，并将在限期内继续履行前述承诺，同时因违反上述承诺给投资者造成损失的，公司将依法赔偿投资者损失，赔偿金额依据公司与投资者协商确定，或中国证监会、司法机关认定。"
      ],
      "matched_keyword": "股东"
    },
    {
      "title_hierarchy": [
        "首次公开发行股票并在创业板上市行股票并在",
        "2、控股股东黄山供销集团、实际控制人黄山市供销社承诺"
      ],
      "content": [
        "本单位保证发行人本次公开发行股票并在创业板上市不存在任何欺诈发行",
        "的情形；若发行人不符合发行上市条件，以欺骗手段骗取发行注册并已经发行上市的，本单位将督促发行人在中国证监会等有权部门确认后 5个工作日内启动股份回购程序，从投资者手中购回本次公开发行的全部股票。"
      ],
      "matched_keyword": "股东"
    },
    {
      "title_hierarchy": [
        "首次公开发行股票并在创业板上市行股票并在",
        "2、控股股东黄山供销集团、实际控制人黄山市供销社承诺"
      ],
      "content": [
        "（1）发行人本次发行及上市的招股说明书及其他信息披露资料不存在虚假记载、误导性陈述或重大遗漏之情形，且本公司对其真实性、准确性、完整性承担个别和连带的法律责任。",
        "（2）若发行人本次发行及上市的招股说明书及其他信息披露资料存在任何虚假记载、误导性陈述或者重大遗漏之情形，且该等情形对判断发行人是否符合法律规定的发行条件构成重大且实质影响的，本公司将利用控股股东地位促使发行人在中国证监会认定有关违法事实后 30 日内启动回购发行人本次公开发行的全部新股工作。",
        "（3）若发行人本次发行及上市的招股说明书及其他信息披露资料存在任何虚假记载、误导性陈述或者重大遗漏之情形，致使投资者在证券交易中遭受损失的，本公司将依法赔偿投资者损失。该等损失的金额以经人民法院认定或与发行人协商确定的金额为准。具体的赔偿标准、赔偿主体范围、赔偿顺序、赔偿金额、赔偿方式等细节内容待上述情形实际发生时，依据最终确定的赔偿方案为准。",
        "上述承诺内容系本公司真实意思表示，本公司自愿接受监管机构、自律组织及社会公众的监督，如违反以上承诺，本公司将依法承担相应责任。"
      ],
      "matched_keyword": "股东"
    },
    {
      "title_hierarchy": [
        "首次公开发行股票并在创业板上市行股票并在",
        "（九）发行人关于股东信息披露的专项承诺"
      ],
      "content": [
        "1、本公司股东中不存在法律法规规定禁止持股的主体直接或间接持有发行人股份。",
        "2、本次发行上市的中介机构或其负责人、高级管理人员、经办人员不存在直接或间接持有本公司股份的情形。",
        "3、发行人股东中不存在以发行人股份进行不当利益输送的情形。",
        "4、直接或间接持有本公司股份的自然人（集合竞价增加的股东除外）不存在证券监督管理相关系统及单位工作人员。",
        "5、本公司保证前述股东信息披露的相关情况真实、准确、完整，不存在任何虚假记载、误导性陈述或重大遗漏。",
        "6、本公司及本公司股东已及时向本次发行的中介机构提供了真实、准确、完整的资料，积极和全面配合了本次发行的中介机构开展尽职调查，依法在本次发行的申报文件中真实、准确、完整地披露了股东信息，履行了信息披露义务。"
      ],
      "matched_keyword": "股东"
    },
    {
      "title_hierarchy": [
        "首次公开发行股票并在创业板上市行股票并在",
        "1、发行人承诺"
      ],
      "content": [
        "公司将切实履行就首次公开发行股票并在创业板上市所作出的所有公开承诺事项，若公司所作承诺未能履行或确已无法履行或无法按期履行的（因相关法律法规、政策变化、自然灾害及其他不可抗力等公司无法控制的客观原因导致的除外），公司拟采取以下措施：",
        "（1）及时、充分披露公司承诺未能履行、无法履行或无法按期履行的具体原因。",
        "（2）在有关监管机关要求的期限内予以纠正，或及时向投资者提出补充承诺或替代承诺。",
        "（3）在股东大会、深圳证券交易所指定信息披露平台及证券监管部门指定报刊上向股东和社会公众投资者道歉。",
        "（4）造成投资者损失的，依法赔偿损失。",
        "（5）有违法所得的，按相关法律法规处理。",
        "如因相关法律法规、政策变化、自然灾害及其他不可抗力等公司无法控制的客观原因导致公司承诺未能履行、确已无法履行或无法按期履行的，公司拟采取以下措施：",
        "（1）及时、充分披露公司承诺未能履行、无法履行或无法按期履行的具体原因。",
        "（2）向投资者提出补充或替代承诺，以尽可能保护投资者的权益。"
      ],
      "matched_keyword": "股东"
    },
    {
      "title_hierarchy": [
        "首次公开发行股票并在创业板上市行股票并在",
        "2、发行人控股股东、实际控制人、其他直接股东、全体董事、监事及高级管理人员承诺"
      ],
      "content": [
        "（1）本承诺人在招股说明书中公开作出的相关承诺中已经包含约束措施的，则以该等承诺中明确的约束措施为准；若本承诺人违反该等承诺，本承诺人同意采取该等承诺中已经明确的约束措施。",
        "（2）本承诺人在招股说明书中公开作出的相关承诺中未包含约束措施的，",
        "若本承诺人违反该等承诺，则同意采取如下约束措施：",
        "①公开披露本承诺人未履行或未及时履行相关承诺的具体原因并向发行人股东及社会公众投资者道歉，同时根据相关法律法规规定及监管部门要求承担相应的法律责任或采取相关替代措施；",
        "②给投资者造成损失的，本承诺人将向投资者依法承担赔偿责任和其他法律责任。"
      ],
      "matched_keyword": "股东"
    },
    {
      "title_hierarchy": [
        "首次公开发行股票并在创业板上市行股票并在",
        "1、控股股东黄山供销集团、实际控制人黄山市供销社关于避免同业竞争的承诺"
      ],
      "content": [
        "（1）本承诺人及本承诺人控制的其他企业均未研发、生产、销售或提供任何与发行人的主营产品和服务构成竞争或可能构成竞争的产品或服务，所经营的业务均未与发行人经营的主营业务构成同业竞争。",
        "（2）本承诺人承诺本承诺人及所控制的其他公司、企业或经济组织，未来不以任何形式直接或间接从事与发行人主营业务或者主营产品/服务相竞争或者构成竞争威胁的业务活动。",
        "（3）若本承诺人及本承诺人所控制的其他公司、企业或经济组织违反上述声明、承诺，并造成发行人经济损失的，本承诺人同意依法承担赔偿责任或其他法律责任。"
      ],
      "matched_keyword": "股东"
    },
    {
      "title_hierarchy": [
        "首次公开发行股票并在创业板上市行股票并在",
        "2、控股股东黄山供销集团、实际控制人黄山市供销社、全体董事、监事、高级管理人员以及其他持有发行人 5%以上股份的股东关于规范和减少关联交易的承诺"
      ],
      "content": [
        "（1）本承诺人将严格按照《公司法》等相关法律法规以及《黄山谷捷股份有限公司章程（草案）》《黄山谷捷股份有限公司关联交易管理制度》等规定行使股东权利，在发行人股东大会对有关涉及本承诺人及本承诺人控制的其他企业事项的关联交易进行表决时，履行回避表决的义务。",
        "（2）本承诺人不利用自身对发行人的影响，谋求发行人在业务合作等方面给予本承诺人及本承诺人控制的其他企业优于市场第三方的权利，不利用自身对发行人的影响，谋求与发行人达成交易的优先权利。",
        "（3）本承诺人将杜绝本承诺人及本承诺人控制的其他企业或经济组织非法占用发行人资金、资产的行为，在任何情况下，不要求发行人违规向本承诺人及本承诺人控制的其他企业提供任何形式的担保。",
        "（4）根据相关法律、法规及规范性文件，为减少并规范关联交易，本承诺人及本承诺人控制的其他企业将尽量避免或减少与发行人及其子公司发生不必要的关联交易；对于无法避免或者有合理原因而发生的关联交易，将遵循市场公正、公平、公开的原则，并依法签订协议，履行合法程序，按照相关法律、法规及规范性文件的规定履行信息披露义务和办理有关审议程序，保证不通过关联交易损害发行人及其他股东的合法权益。",
        "若本承诺人及本承诺人控制的其他企业违反上述承诺，并造成发行人经济损失的，本承诺人同意依法承担赔偿责任或其他法律责任。"
      ],
      "matched_keyword": "股东"
    },
    {
      "title_hierarchy": [
        "首次公开发行股票并在创业板上市行股票并在",
        "3、控股股东黄山供销集团、实际控制人黄山市供销社、持股 5%以上的股东、董事、监事、高级管理人员关于避免资金占用的承诺"
      ],
      "content": [
        "（1）本承诺人及本承诺人控制的企业现时不存在任何依照有关法律、法规、规范性文件应披露而未披露的资金占用，包括但不限于以借款、代偿债务、代垫款项等方式占用或转移发行人及其控股子公司资金或资产的情形。",
        "（2）本承诺人及本承诺人控制的企业将严格遵守有关法律、法规、规范性文件的规定，未来不以借款、代偿债务、代垫款项或者其他任何直接或间接的方式占用发行人及其控股子公司的资金，不与发行人及其控股子公司发生非经营性资金往来。",
        "（3）本承诺人将严格履行承诺事项，并督促本承诺人控制的企业严格履行本承诺事项。如相关方违反本承诺给发行人及其控股子公司造成损失的，本承诺人愿意承担由此产生的全部责任，充分赔偿或补偿由此给发行人及其控股子公司造成的所有直接或间接损失。"
      ],
      "matched_keyword": "股东"
    },
    {
      "title_hierarchy": [
        "首次公开发行股票并在创业板上市行股票并在",
        "4、控股股东黄山供销集团、实际控制人黄山市供销社关于社保、公积金缴纳事宜的承诺"
      ],
      "content": [
        "如应社会保障主管部门或住房公积金主管部门的要求或决定，发行人及其子公司需要为员工补缴社会保险金、住房公积金或因未为员工缴纳社会保险金、住房公积金而承担任何罚款或损失，本单位将全部承担发行人及其子公司应补缴的社会保险、住房公积金和由此产生的滞纳金、罚款以及赔偿等费用，保障发行人及其子公司不会因此遭受损失。"
      ],
      "matched_keyword": "股东"
    },
    {
      "title_hierarchy": [
        "首次公开发行股票并在创业板上市行股票并在",
        "（十二）关于业绩下滑时延长股份锁定期的承诺"
      ],
      "content": [
        "控股股东黄山供销集团、实际控制人黄山市供销社承诺：",
        "发行人上市当年较上市前一年扣除非经常性损益后归母净利润下滑 50%以上的，延长本承诺人届时所持股份锁定期限 6 个月；",
        "发行人上市第二年较上市前一年扣除非经常性损益后归母净利润下滑 50%以上的，在前项基础上延长承诺人届时所持股份锁定期限 6个月；",
        "发行人上市第三年较上市前一年扣除非经常性损益后归母净利润下滑 50%以上的，在前两项基础上延长承诺人届时所持股份锁定期 6个月。"
      ],
      "matched_keyword": "股东"
    },
    {
      "title_hierarchy": [
        "首次公开发行股票并在创业板上市行股票并在",
        "（一）股东大会的运行情况"
      ],
      "content": [
        "2022 年 9 月 8 日，公司创立大会审议通过了《公司章程》和《股东大会议事规则》，对股东大会的职权、表决方式等作出明确规定。《公司章程》《股东大会议事规则》符合《公司法》《上市公司治理准则》等相关法律法规的要求。",
        "自股份公司成立以来，股东大会严格按照《公司章程》和《股东大会议事规则》的规定召开，运行规范。自股份公司成立以来，共召开 8 次股东大会，股东或股东代表出席会议情况符合相关规定。"
      ],
      "matched_keyword": "股东"
    },
    {
      "title_hierarchy": [
        "首次公开发行股票并在创业板上市行股票并在",
        "（四）独立董事制度的运行情况"
      ],
      "content": [
        "公司根据《公司法》等法律、法规、规章和《公司章程》制定了《独立董事工作制度》，对独立董事的任职资格，提名、选举及更换，职权等作出明确规定。公司现有 3 名独立董事，占全部董事人数的 1/3，其中包括一名会计专业人士，均经股东大会选举产生。",
        "独立董事自任职以来，严格按照《公司章程》《董事会议事规则》《独立董事工作制度》等相关制度的规定行使权利、履行义务，积极参与公司决策，为公司治理结构的完善和规范运作起到了积极作用。"
      ],
      "matched_keyword": "股东"
    },
    {
      "title_hierarchy": [
        "首次公开发行股票并在创业板上市行股票并在",
        "（五）董事会秘书制度的运行情况"
      ],
      "content": [
        "公司设董事会秘书 1名，由董事长提名，董事会聘任或解聘。公司制定了《董事会秘书工作制度》，对董事会秘书的任职资格、职权、聘任及解聘等进行了明",
        "确规定。董事会秘书作为公司的高级管理人员，负责公司股东大会和董事会会议的筹备、文件保管、信息披露等事宜。",
        "报告期内，公司董事会秘书严格按照有关法律法规、《公司章程》及《董事会秘书工作制度》履行了职责。"
      ],
      "matched_keyword": "股东"
    },
    {
      "title_hierarchy": [
        "首次公开发行股票并在创业板上市行股票并在",
        "4、实施主体"
      ],
      "content": [
        "本项目的实施主体为本公司，不涉及与他人合作，亦不涉及向控股股东、实际控制人及其关联方收购资产。"
      ],
      "matched_keyword": "股东"
    },
    {
      "title_hierarchy": [
        "首次公开发行股票并在创业板上市行股票并在",
        "4、实施主体"
      ],
      "content": [
        "本项目的实施主体为本公司，不涉及与他人合作，亦不涉及向控股股东、实际控制人及其关联方收购资产。"
      ],
      "matched_keyword": "股东"
    }
  ]
}